Workbook
Name solver_adj: Summary!#REF!
Name solver_cvg: 0.0001
Name solver_drv: 1
Name solver_eng: 1
Name solver_est: 1
Name solver_itr: 2147483647
Name solver_mip: 2147483647
Name solver_mni: 30
Name solver_mrt: 0.075
Name solver_msl: 2
Name solver_neg: 1
Name solver_nod: 2147483647
Name solver_num: 0
Name solver_nwt: 1
Name solver_opt: Summary!#REF!
Name solver_pre: 0.000001
Name solver_rbv: 1
Name solver_rlx: 2
Name solver_rsd: 0
Name solver_scl: 1
Name solver_sho: 2
Name solver_ssz: 100
Name solver_tim: 2147483647
Name solver_tol: 0.01
Name solver_typ: 3
Name solver_val: 0
Name solver_ver: 3
Name Year: Reference!$B$2:$B$2060
Name Month: Reference!$C$2:$C$2060
Name Weekday: Reference!$D$2:$D$2060

Sheet Capex
B2: # | C2: Capex | D2: Unit | E2: Cost
B3: I | C3: Initial outlay
B4: 1 | C4: Capex | E4: 2959200000
C5: Design | D5: [VND] | G5: =SUM(E5:E9) -> 0
C6: Construction + Fit-in + Fit-out | D6: [VND]
C7: Interior & Madrix Lighting | D7: [VND]
C8: Loose Furniture | D8: [VND]
C9: Decor & Sinage | D9: [VND]
C10: Sound System + DJ Equipments | D10: [VND]
C11: Bar + Kitchen Equipments | D11: [VND]
C12: Sanitary Wares | D12: [VND]
C13: Fire Safety Equipments | D13: [VND]
C14: Contigency | D14: [VND]
C15: BOH Fixture + Supply
B16: 2 | C16: Working capital | D16: [VND] | E16: =E52 -> 7.346417e+08
B22: 3 | C22: Pre-opening costs | D22: [VND] | E22: =E40 -> 368000000
C31: Total Investment | D31: [VND] | E31: =E4+E16+E22 -> 4061841703
B32: II | C32: Maintenance capex
C33: 1 | D33: [VND] | E33: 0
C34: =C33+1 -> 2 | D34: [VND]
C35: =C34+1 -> 3 | D35: [VND]
C36: =C35+1 -> 4 | D36: [VND]
C37: =C36+1 -> 5 | D37: [VND]
B40: Pre-opening Costs: | E40: =SUM(E41:E50) -> 368000000
C41: Inventory (Food + Drink) | E41: 142000000 | G41: (1 month)
C42: Take away Set | E42: =Assumption!G39 -> 10000000
C43: MKT printing | E43: =Assumption!G40 -> 5000000
C44: Contigency | E44: =Assumption!G45 -> 10000000
C45: Scent & music subcription | E45: =Assumption!G37 -> 1000000
C46: Licenses | E46: 75000000
C47: 1 rental month - construction | E47: 75000000
C48: Grand-opening | E48: 50000000
B52: Working Cap | E52: =SUM(E53:E61)*2 -> 7.346417e+08 | G52: (2 months)
C53: Labor Costs | E53: =Assumption!G36 -> 3.1732085e+08
C54: Electricity & water expense | E54: =Assumption!G41 -> 30000000
C55: Internet & waste mgmt expense | E55: =Assumption!G42 -> 5000000
C56: Monthly maintenance expense + Pest control | E56: =Assumption!G43 -> 10000000
C57: Parking expense | E57: =Assumption!G44 -> 5000000

Sheet Assumption
B1: A | C1: I.S. ITEMS | I1: B | J1: B.S. ITEMS
B3: # | C3: Revenue Drivers | D3: Unit | E3: GR | F3: PR | G3: Total | I3: # | J3: Financing | K3: Unit | L3: Input
B4: 1 | C4: Sun - Thu | I4: 1 | J4: Term loan
C5: Spending | D5: [VND] | E5: 200000 | F5: 0 | J5: Borrowings | K5: [VND] | L5: 0
C6: Seat occupied | D6: [seat] | E6: 125 | F6: 0 | G6: =SUM(E6:F6) -> 125 | J6: Tenor | K6: [year] | L6: 0
C7: %implied occupancy | D7: [%] | E7: =E6/$G$20 -> 1.6666667 | F7: =F6/$G$20 -> 0 | G7: =G6/$G$20 -> 1.6666667 | J7: Grace period | K7: [year] | L7: 0
C8: Annual increase | D8: [seat] | E8: 0 | F8: 0 | G8: 0 | J8: Interest expense | K8: [%] | L8: 0
C9: Stable seat occupied | D9: [seat] | E9: 70 | F9: 0 | G9: =SUM(E9:F9) -> 70 | I9: 2 | J9: Capital structure
C10: %implied occupancy | D10: [%] | E10: =E9/$G$20 -> 0.93333333 | F10: =F9/$G$20 -> 0 | G10: =G9/$G$20 -> 0.93333333 | J10: Debt | K10: [%] | L10: 0
B11: 2 | C11: Fri - Sat | J11: Cost of debt | K11: [%] | L11: 0
C12: Spending | D12: [VND] | E12: 700000 | F12: 0 | J12: Equity | K12: [%] | L12: 0
C13: Seat occupied | D13: [seat] | E13: 150 | F13: 0 | G13: =SUM(E13:F13) -> 150 | J13: Cost of equity | K13: [%] | L13: 0
C14: %implied occupancy | D14: [%] | E14: =E13/$G$20 -> 2 | F14: =F13/$G$20 -> 0 | G14: =G13/$G$20 -> 2 | J14: WACC | K14: [%] | L14: 0
C15: Annual increase | D15: [seat] | E15: 0 | F15: 0 | G15: 0 | Q15: làm sao để giữ chân khách, khách không bị chán sau 2 năm
C16: Stable seat occupied | D16: [seat] | E16: 70 | F16: 0 | G16: =SUM(E16:F16) -> 70 | I16: khả năng khách tới nghe jazz, ngồi bao lâu, chi bao nhiêu | Q16: nhân sự
C17: %implied occupancy | D17: [%] | E17: =E16/$G$20 -> 0.93333333 | F17: =F16/$G$20 -> 0 | G17: =G16/$G$20 -> 0.93333333 | I17: cà phê sáng có bán cover được chi phí nhân viên + fixed costs của ban ngày ko | Q17: event collab vs các bên
B18: 3 | C18: General assumptions | I18: doanh thu tập trung nhất vào khung giờ từ 7pm trở đi
C19: Area | D19: [sqm] | G19: 150 | I19: bán thêm gói event, workshop ban ngày cho tầng 1
C20: Capacity | D20: [seat] | G20: 75 | I20: menu food - drinks -> chất lượng, cạnh tranh => nguồn thu chính
C21: Escalation rate | D21: [%] | G21: 0.05 | I21: làm event có special DJ sẽ bán ntn?
C22: Ramp-up schedule | D22: [month] | G22: 6 | I22: làm sao để khách biết đến mình => mkt plan
C23: LNY effect | D23: [%] | G23: -0.6
C24: Xmas & NYE effect | D24: [%] | G24: 0.2
J25: No-event daily Sun-Thu | Q25: With event Fri-Sat | R25: 0.85416667 | S25: 0.91666667 | T25: 10:00PM - 25:00 | U25: 0.041666667
B26: # | C26: Cost Structure | E26: Unit | G26: Input | I26: # | J26: Revenue Drivers | K26: Unit | L26: GR | M26: PR | N26: Total | P26: # | Q26: Revenue Drivers | R26: Unit | S26: GR | T26: PR | U26: Total
B27: 1 | C27: Defect | I27: 1 | J27: Mon-Tue-Wed-Thu | P27: 1
C28: Food | E28: [%] | G28: 0.01 | J28: Spending | K28: [VND] | L28: 160000 | M28: 0 | Q28: Spending | R28: [VND] | T28: 0
C29: Drink | E29: [%] | G29: 0.02 | J29: Seat occupied | K29: [seat] | L29: 75 | M29: 0 | N29: =SUM(L29:M29) -> 75 | Q29: Seat occupied | R29: [seat] | S29: 50 | T29: 0 | U29: =SUM(S29:T29) -> 50
B30: 2 | C30: COGS | J30: %implied occupancy | K30: [%] | L30: =L29/$G$20 -> 1 | M30: =M29/$G$20 -> 0 | N30: =N29/$G$20 -> 1 | Q30: %implied occupancy | R30: [%] | S30: =S29/$G$20 -> 0.66666667 | T30: =T29/$G$20 -> 0 | U30: =U29/$G$20 -> 0.66666667
C31: Food | E31: [%] | G31: 0.35 | J31: Annual increase | K31: [seat] | L31: 0 | M31: 0 | N31: 0 | Q31: Annual increase | R31: [seat] | S31: 0 | T31: 0 | U31: 0
C32: Drink | E32: [%] | G32: 0.26 | J32: Stable seat occupied | K32: [seat] | L32: 75 | M32: 0 | N32: =SUM(L32:M32) -> 75 | Q32: Stable seat occupied | R32: [seat] | S32: 75 | T32: 0 | U32: =SUM(S32:T32) -> 75
B33: 3 | C33: Rental expense | J33: %implied occupancy | K33: [%] | L33: =L32/$G$20 -> 1 | M33: =M32/$G$20 -> 0 | N33: =N32/$G$20 -> 1 | Q33: %implied occupancy | R33: [%] | S33: =S32/$G$20 -> 1 | T33: =T32/$G$20 -> 0 | U33: =U32/$G$20 -> 1
C34: Monthly fee | E34: [VND/month] | G34: 75000000 | I34: 2 | J34: Sun | P34: 2 | Q34: Fri - Sun
C35: Escalation (biannually) | E35: [%] | G35: 0.08 | J35: Spending | K35: [VND] | L35: 200000 | M35: 0 | Q35: Spending | R35: [VND] | S35: 800000 | T35: 0
B36: 4 | C36: Labor Expense | E36: [VND/month] | G36: =Model!O154 -> 3.1732085e+08 | J36: Seat occupied | K36: [seat] | L36: 75 | M36: 0 | N36: =SUM(L36:M36) -> 75 | Q36: Seat occupied | R36: [seat] | S36: 125 | T36: 0 | U36: =SUM(S36:T36) -> 125
C37: Scent & Music Subscriptions | E37: [VND/month] | G37: 1000000 | J37: %implied occupancy | K37: [%] | L37: =L36/$G$20 -> 1 | M37: =M36/$G$20 -> 0 | N37: =N36/$G$20 -> 1 | Q37: %implied occupancy | R37: [%] | S37: =S36/$G$20 -> 1.6666667 | T37: =T36/$G$20 -> 0 | U37: =U36/$G$20 -> 1.6666667
B38: 5 | C38: Other fixed costs | G38: =SUM(G39:G45) -> 75000000 | J38: Annual increase | K38: [seat] | L38: 0 | M38: 0 | N38: 0 | Q38: Annual increase | R38: [seat] | S38: 0 | T38: 0 | U38: 0
C39: Take away set | E39: [VND/month] | G39: 10000000 | J39: Stable seat occupied | K39: [seat] | L39: 75 | M39: 0 | N39: =SUM(L39:M39) -> 75 | Q39: Stable seat occupied | R39: [seat] | S39: 75 | T39: 0 | U39: =SUM(S39:T39) -> 75
C40: Printing | E40: [VND/month] | G40: 5000000 | J40: %implied occupancy | K40: [%] | L40: =L39/$G$20 -> 1 | M40: =M39/$G$20 -> 0 | N40: =N39/$G$20 -> 1 | Q40: %implied occupancy | R40: [%] | S40: =S39/$G$20 -> 1 | T40: =T39/$G$20 -> 0 | U40: =U39/$G$20 -> 1
C41: Electricity & water expense | E41: [VND/month] | G41: 30000000
C42: Internet & waste mgmt expense | E42: [VND/month] | G42: 5000000
C43: Monthly maintenance expense + Pest control | E43: [VND/month] | G43: 10000000
C44: Parking expense | E44: [VND/month] | G44: 5000000 | H44: có thể phải share bãi giữ xe cho khách cf sáng
C45: Contingency | E45: [VND/month] | G45: 10000000
C46: Cost escalation | E46: [%] | G46: 0.04 | H46: based on VN inflation rate
B47: 6 | C47: Variable costs
C48: Food Cost | E48: [%] | G48: 0.05
C49: Drink Cost | E49: [%] | G49: 0.05
C50: G&A expenses | E50: [%] | G50: 0.05
C51: Marketing expenses | E51: [%] | G51: 0.01

Sheet Model
B1: SUPPORTING SCHEDULE
B2: Period | G2: 1 | H2: =IF(MONTH(H5)=MONTH($G$5),G2+1,G2) -> 1 | I2: =IF(MONTH(I5)=MONTH($G$5),H2+1,H2) -> 1 | J2: =IF(MONTH(J5)=MONTH($G$5),I2+1,I2) -> 1 | K2: =IF(MONTH(K5)=MONTH($G$5),J2+1,J2) -> 1 | L2: =IF(MONTH(L5)=MONTH($G$5),K2+1,K2) -> 1 | M2: =IF(MONTH(M5)=MONTH($G$5),L2+1,L2) -> 1 | N2: =IF(MONTH(N5)=MONTH($G$5),M2+1,M2) -> 1 | O2: =IF(MONTH(O5)=MONTH($G$5),N2+1,N2) -> 1 | ... BN2: =IF(MONTH(BN5)=MONTH($G$5),BM2+1,BM2) -> 5
B3: Year | G3: =YEAR(G5) -> 2026 | H3: =YEAR(H5) -> 2026 | I3: =YEAR(I5) -> 2026 | J3: =YEAR(J5) -> 2026 | K3: =YEAR(K5) -> 2026 | L3: =YEAR(L5) -> 2026 | M3: =YEAR(M5) -> 2026 | N3: =YEAR(N5) -> 2027 | ... BN3: =YEAR(BN5) -> 2031
B4: Month | G4: =VLOOKUP(MONTH(G5),Reference!$H$12:$I$23,2,FALSE) -> Jun | H4: =VLOOKUP(MONTH(H5),Reference!$H$12:$I$23,2,FALSE) -> Jul | I4: =VLOOKUP(MONTH(I5),Reference!$H$12:$I$23,2,FALSE) -> Aug | J4: =VLOOKUP(MONTH(J5),Reference!$H$12:$I$23,2,FALSE) -> Sep | K4: =VLOOKUP(MONTH(K5),Reference!$H$12:$I$23,2,FALSE) -> Oct | L4: =VLOOKUP(MONTH(L5),Reference!$H$12:$I$23,2,FALSE) -> Nov | M4: =VLOOKUP(MONTH(M5),Reference!$H$12:$I$23,2,FALSE) -> Dec | N4: =VLOOKUP(MONTH(N5),Reference!$H$12:$I$23,2,FALSE) -> Jan | ... BN4: =VLOOKUP(MONTH(BN5),Reference!$H$12:$I$23,2,FALSE) -> May
B5: Date | G5: 46174 | H5: =EOMONTH(G5,1) -> 46234 | I5: =EOMONTH(H5,1) -> 46265 | J5: =EOMONTH(I5,1) -> 46295 | K5: =EOMONTH(J5,1) -> 46326 | L5: =EOMONTH(K5,1) -> 46356 | M5: =EOMONTH(L5,1) -> 46387 | N5: =EOMONTH(M5,1) -> 46418 | O5: =EOMONTH(N5,1) -> 46446 | ... BN5: =EOMONTH(BM5,1) -> 47999
B7: A | C7: REVENUE DRIVERS
B9: 1 | C9: Working schedule
C10: Monday | E10: 1 | G10: =COUNTIFS(Year,G$3,Month,MONTH(G$5),Weekday,$C10)*$E10 -> 5 | H10: =COUNTIFS(Year,H$3,Month,MONTH(H$5),Weekday,$C10)*$E10 -> 4 | I10: =COUNTIFS(Year,I$3,Month,MONTH(I$5),Weekday,$C10)*$E10 -> 5 | J10: =COUNTIFS(Year,J$3,Month,MONTH(J$5),Weekday,$C10)*$E10 -> 4 | K10: =COUNTIFS(Year,K$3,Month,MONTH(K$5),Weekday,$C10)*$E10 -> 4 | L10: =COUNTIFS(Year,L$3,Month,MONTH(L$5),Weekday,$C10)*$E10 -> 5 | M10: =COUNTIFS(Year,M$3,Month,MONTH(M$5),Weekday,$C10)*$E10 -> 4 | N10: =COUNTIFS(Year,N$3,Month,MONTH(N$5),Weekday,$C10)*$E10 -> 4 | ... BN10: =COUNTIFS(Year,BN$3,Month,MONTH(BN$5),Weekday,$C10)*$E10 -> 4
C11: Tuesday | E11: 1 | G11: =COUNTIFS(Year,G$3,Month,MONTH(G$5),Weekday,$C11)*$E11 -> 5 | H11: =COUNTIFS(Year,H$3,Month,MONTH(H$5),Weekday,$C11)*$E11 -> 4 | I11: =COUNTIFS(Year,I$3,Month,MONTH(I$5),Weekday,$C11)*$E11 -> 4 | J11: =COUNTIFS(Year,J$3,Month,MONTH(J$5),Weekday,$C11)*$E11 -> 5 | K11: =COUNTIFS(Year,K$3,Month,MONTH(K$5),Weekday,$C11)*$E11 -> 4 | L11: =COUNTIFS(Year,L$3,Month,MONTH(L$5),Weekday,$C11)*$E11 -> 4 | M11: =COUNTIFS(Year,M$3,Month,MONTH(M$5),Weekday,$C11)*$E11 -> 5 | N11: =COUNTIFS(Year,N$3,Month,MONTH(N$5),Weekday,$C11)*$E11 -> 4 | ... BN11: =COUNTIFS(Year,BN$3,Month,MONTH(BN$5),Weekday,$C11)*$E11 -> 4
C12: Wednesday | E12: 1 | G12: =COUNTIFS(Year,G$3,Month,MONTH(G$5),Weekday,$C12)*$E12 -> 4 | H12: =COUNTIFS(Year,H$3,Month,MONTH(H$5),Weekday,$C12)*$E12 -> 5 | I12: =COUNTIFS(Year,I$3,Month,MONTH(I$5),Weekday,$C12)*$E12 -> 4 | J12: =COUNTIFS(Year,J$3,Month,MONTH(J$5),Weekday,$C12)*$E12 -> 5 | K12: =COUNTIFS(Year,K$3,Month,MONTH(K$5),Weekday,$C12)*$E12 -> 4 | L12: =COUNTIFS(Year,L$3,Month,MONTH(L$5),Weekday,$C12)*$E12 -> 4 | M12: =COUNTIFS(Year,M$3,Month,MONTH(M$5),Weekday,$C12)*$E12 -> 5 | N12: =COUNTIFS(Year,N$3,Month,MONTH(N$5),Weekday,$C12)*$E12 -> 4 | ... BN12: =COUNTIFS(Year,BN$3,Month,MONTH(BN$5),Weekday,$C12)*$E12 -> 4
C13: Thursday | E13: 1 | G13: =COUNTIFS(Year,G$3,Month,MONTH(G$5),Weekday,$C13)*$E13 -> 4 | H13: =COUNTIFS(Year,H$3,Month,MONTH(H$5),Weekday,$C13)*$E13 -> 5 | I13: =COUNTIFS(Year,I$3,Month,MONTH(I$5),Weekday,$C13)*$E13 -> 4 | J13: =COUNTIFS(Year,J$3,Month,MONTH(J$5),Weekday,$C13)*$E13 -> 4 | K13: =COUNTIFS(Year,K$3,Month,MONTH(K$5),Weekday,$C13)*$E13 -> 5 | L13: =COUNTIFS(Year,L$3,Month,MONTH(L$5),Weekday,$C13)*$E13 -> 4 | M13: =COUNTIFS(Year,M$3,Month,MONTH(M$5),Weekday,$C13)*$E13 -> 5 | N13: =COUNTIFS(Year,N$3,Month,MONTH(N$5),Weekday,$C13)*$E13 -> 4 | ... BN13: =COUNTIFS(Year,BN$3,Month,MONTH(BN$5),Weekday,$C13)*$E13 -> 5
C14: Friday | E14: 1 | G14: =COUNTIFS(Year,G$3,Month,MONTH(G$5),Weekday,$C14)*$E14 -> 4 | H14: =COUNTIFS(Year,H$3,Month,MONTH(H$5),Weekday,$C14)*$E14 -> 5 | I14: =COUNTIFS(Year,I$3,Month,MONTH(I$5),Weekday,$C14)*$E14 -> 4 | J14: =COUNTIFS(Year,J$3,Month,MONTH(J$5),Weekday,$C14)*$E14 -> 4 | K14: =COUNTIFS(Year,K$3,Month,MONTH(K$5),Weekday,$C14)*$E14 -> 5 | L14: =COUNTIFS(Year,L$3,Month,MONTH(L$5),Weekday,$C14)*$E14 -> 4 | M14: =COUNTIFS(Year,M$3,Month,MONTH(M$5),Weekday,$C14)*$E14 -> 4 | N14: =COUNTIFS(Year,N$3,Month,MONTH(N$5),Weekday,$C14)*$E14 -> 5 | ... BN14: =COUNTIFS(Year,BN$3,Month,MONTH(BN$5),Weekday,$C14)*$E14 -> 5
C15: Saturday | E15: 1 | G15: =COUNTIFS(Year,G$3,Month,MONTH(G$5),Weekday,$C15)*$E15 -> 4 | H15: =COUNTIFS(Year,H$3,Month,MONTH(H$5),Weekday,$C15)*$E15 -> 4 | I15: =COUNTIFS(Year,I$3,Month,MONTH(I$5),Weekday,$C15)*$E15 -> 5 | J15: =COUNTIFS(Year,J$3,Month,MONTH(J$5),Weekday,$C15)*$E15 -> 4 | K15: =COUNTIFS(Year,K$3,Month,MONTH(K$5),Weekday,$C15)*$E15 -> 5 | L15: =COUNTIFS(Year,L$3,Month,MONTH(L$5),Weekday,$C15)*$E15 -> 4 | M15: =COUNTIFS(Year,M$3,Month,MONTH(M$5),Weekday,$C15)*$E15 -> 4 | N15: =COUNTIFS(Year,N$3,Month,MONTH(N$5),Weekday,$C15)*$E15 -> 5 | ... BN15: =COUNTIFS(Year,BN$3,Month,MONTH(BN$5),Weekday,$C15)*$E15 -> 5
C16: Sunday | E16: 1 | G16: =COUNTIFS(Year,G$3,Month,MONTH(G$5),Weekday,$C16)*$E16 -> 4 | H16: =COUNTIFS(Year,H$3,Month,MONTH(H$5),Weekday,$C16)*$E16 -> 4 | I16: =COUNTIFS(Year,I$3,Month,MONTH(I$5),Weekday,$C16)*$E16 -> 5 | J16: =COUNTIFS(Year,J$3,Month,MONTH(J$5),Weekday,$C16)*$E16 -> 4 | K16: =COUNTIFS(Year,K$3,Month,MONTH(K$5),Weekday,$C16)*$E16 -> 4 | L16: =COUNTIFS(Year,L$3,Month,MONTH(L$5),Weekday,$C16)*$E16 -> 5 | M16: =COUNTIFS(Year,M$3,Month,MONTH(M$5),Weekday,$C16)*$E16 -> 4 | N16: =COUNTIFS(Year,N$3,Month,MONTH(N$5),Weekday,$C16)*$E16 -> 5 | ... BN16: =COUNTIFS(Year,BN$3,Month,MONTH(BN$5),Weekday,$C16)*$E16 -> 4
C17: Total | G17: =SUM(G10:G16) -> 30 | H17: =SUM(H10:H16) -> 31 | I17: =SUM(I10:I16) -> 31 | J17: =SUM(J10:J16) -> 30 | K17: =SUM(K10:K16) -> 31 | L17: =SUM(L10:L16) -> 30 | M17: =SUM(M10:M16) -> 31 | N17: =SUM(N10:N16) -> 31 | ... BN17: =SUM(BN10:BN16) -> 31
B19: 2 | C19: Capacity adjustment
C20: Ramp-up capacity | E20: 0.5 | G20: =E20 -> 0.5 | H20: =MIN(G20+(1-$E$20)/(Assumption!$G$22-1),100%) -> 0.6 | I20: =MIN(H20+(1-$E$20)/(Assumption!$G$22-1),100%) -> 0.7 | J20: =MIN(I20+(1-$E$20)/(Assumption!$G$22-1),100%) -> 0.8 | K20: =MIN(J20+(1-$E$20)/(Assumption!$G$22-1),100%) -> 0.9 | L20: =MIN(K20+(1-$E$20)/(Assumption!$G$22-1),100%) -> 1 | M20: =MIN(L20+(1-$E$20)/(Assumption!$G$22-1),100%) -> 1 | N20: =MIN(M20+(1-$E$20)/(Assumption!$G$22-1),100%) -> 1 | O20: =MIN(N20+(1-$E$20)/(Assumption!$G$22-1),100%) -> 1 | ... BN20: =MIN(BM20+(1-$E$20)/(Assumption!$G$22-1),100%) -> 1
C21: LNY adjustment | E21: Feb | G21: =IF(G$4=$E21,Assumption!$G$23,0) -> 0 | H21: =IF(H$4=$E21,Assumption!$G$23,0) -> 0 | I21: =IF(I$4=$E21,Assumption!$G$23,0) -> 0 | J21: =IF(J$4=$E21,Assumption!$G$23,0) -> 0 | K21: =IF(K$4=$E21,Assumption!$G$23,0) -> 0 | L21: =IF(L$4=$E21,Assumption!$G$23,0) -> 0 | M21: =IF(M$4=$E21,Assumption!$G$23,0) -> 0 | N21: =IF(N$4=$E21,Assumption!$G$23,0) -> 0 | ... BN21: =IF(BN$4=$E21,Assumption!$G$23,0) -> 0
C22: Xmas & NYE adjustment | E22: Dec | G22: =IF(G$4=$E22,Assumption!$G$24,0) -> 0 | H22: =IF(H$4=$E22,Assumption!$G$24,0) -> 0 | I22: =IF(I$4=$E22,Assumption!$G$24,0) -> 0 | J22: =IF(J$4=$E22,Assumption!$G$24,0) -> 0 | K22: =IF(K$4=$E22,Assumption!$G$24,0) -> 0 | L22: =IF(L$4=$E22,Assumption!$G$24,0) -> 0 | M22: =IF(M$4=$E22,Assumption!$G$24,0) -> 0.2 | N22: =IF(N$4=$E22,Assumption!$G$24,0) -> 0 | ... BN22: =IF(BN$4=$E22,Assumption!$G$24,0) -> 0
C23: Total effect on capacity | G23: =G20*(1+G21)*(1+G22) -> 0.5 | H23: =H20*(1+H21)*(1+H22) -> 0.6 | I23: =I20*(1+I21)*(1+I22) -> 0.7 | J23: =J20*(1+J21)*(1+J22) -> 0.8 | K23: =K20*(1+K21)*(1+K22) -> 0.9 | L23: =L20*(1+L21)*(1+L22) -> 1 | M23: =M20*(1+M21)*(1+M22) -> 1.2 | N23: =N20*(1+N21)*(1+N22) -> 1 | ... BN23: =BN20*(1+BN21)*(1+BN22) -> 1
B25: 3 | C25: Daily order count (pre-adjustment)
C26: On Mon - Thu | G26: =SUM(G27:G28) -> 125 | H26: =SUM(H27:H28) -> 70 | I26: =SUM(I27:I28) -> 70 | J26: =SUM(J27:J28) -> 70 | K26: =SUM(K27:K28) -> 70 | L26: =SUM(L27:L28) -> 70 | M26: =SUM(M27:M28) -> 70 | N26: =SUM(N27:N28) -> 70 | ... BN26: =SUM(BN27:BN28) -> 70
C27: General seats | G27: =Assumption!E6 -> 125 | H27: =MIN(G27+Assumption!$E$8*(Model!H$2-Model!G$2),Assumption!$E$9) -> 70 | I27: =MIN(H27+Assumption!$E$8*(Model!I$2-Model!H$2),Assumption!$E$9) -> 70 | J27: =MIN(I27+Assumption!$E$8*(Model!J$2-Model!I$2),Assumption!$E$9) -> 70 | K27: =MIN(J27+Assumption!$E$8*(Model!K$2-Model!J$2),Assumption!$E$9) -> 70 | L27: =MIN(K27+Assumption!$E$8*(Model!L$2-Model!K$2),Assumption!$E$9) -> 70 | M27: =MIN(L27+Assumption!$E$8*(Model!M$2-Model!L$2),Assumption!$E$9) -> 70 | N27: =MIN(M27+Assumption!$E$8*(Model!N$2-Model!M$2),Assumption!$E$9) -> 70 | O27: =MIN(N27+Assumption!$E$8*(Model!O$2-Model!N$2),Assumption!$E$9) -> 70 | ... BN27: =MIN(BM27+Assumption!$E$8*(Model!BN$2-Model!BM$2),Assumption!$E$9) -> 70
C28: PDR | G28: =Assumption!F6 -> 0 | H28: =MIN(G28+Assumption!$F$8*(Model!H$2-Model!G$2),Assumption!$F$9) -> 0 | I28: =MIN(H28+Assumption!$F$8*(Model!I$2-Model!H$2),Assumption!$F$9) -> 0 | J28: =MIN(I28+Assumption!$F$8*(Model!J$2-Model!I$2),Assumption!$F$9) -> 0 | K28: =MIN(J28+Assumption!$F$8*(Model!K$2-Model!J$2),Assumption!$F$9) -> 0 | L28: =MIN(K28+Assumption!$F$8*(Model!L$2-Model!K$2),Assumption!$F$9) -> 0 | M28: =MIN(L28+Assumption!$F$8*(Model!M$2-Model!L$2),Assumption!$F$9) -> 0 | N28: =MIN(M28+Assumption!$F$8*(Model!N$2-Model!M$2),Assumption!$F$9) -> 0 | O28: =MIN(N28+Assumption!$F$8*(Model!O$2-Model!N$2),Assumption!$F$9) -> 0 | ... BN28: =MIN(BM28+Assumption!$F$8*(Model!BN$2-Model!BM$2),Assumption!$F$9) -> 0
C29: On Fri - Sun | G29: =SUM(G30:G31) -> 150 | H29: =SUM(H30:H31) -> 70 | I29: =SUM(I30:I31) -> 70 | J29: =SUM(J30:J31) -> 70 | K29: =SUM(K30:K31) -> 70 | L29: =SUM(L30:L31) -> 70 | M29: =SUM(M30:M31) -> 70 | N29: =SUM(N30:N31) -> 70 | ... BN29: =SUM(BN30:BN31) -> 70
C30: General seats | G30: =Assumption!E13 -> 150 | H30: =MIN(G30+Assumption!$E$15*(Model!H$2-Model!G$2),Assumption!$E$16) -> 70 | I30: =MIN(H30+Assumption!$E$15*(Model!I$2-Model!H$2),Assumption!$E$16) -> 70 | J30: =MIN(I30+Assumption!$E$15*(Model!J$2-Model!I$2),Assumption!$E$16) -> 70 | K30: =MIN(J30+Assumption!$E$15*(Model!K$2-Model!J$2),Assumption!$E$16) -> 70 | L30: =MIN(K30+Assumption!$E$15*(Model!L$2-Model!K$2),Assumption!$E$16) -> 70 | M30: =MIN(L30+Assumption!$E$15*(Model!M$2-Model!L$2),Assumption!$E$16) -> 70 | N30: =MIN(M30+Assumption!$E$15*(Model!N$2-Model!M$2),Assumption!$E$16) -> 70 | O30: =MIN(N30+Assumption!$E$15*(Model!O$2-Model!N$2),Assumption!$E$16) -> 70 | ... BN30: =MIN(BM30+Assumption!$E$15*(Model!BN$2-Model!BM$2),Assumption!$E$16) -> 70
C31: PDR | G31: =Assumption!F13 -> 0 | H31: =MIN(G31+Assumption!$F$15*(Model!H$2-Model!G$2),Assumption!$F$16) -> 0 | I31: =MIN(H31+Assumption!$F$15*(Model!I$2-Model!H$2),Assumption!$F$16) -> 0 | J31: =MIN(I31+Assumption!$F$15*(Model!J$2-Model!I$2),Assumption!$F$16) -> 0 | K31: =MIN(J31+Assumption!$F$15*(Model!K$2-Model!J$2),Assumption!$F$16) -> 0 | L31: =MIN(K31+Assumption!$F$15*(Model!L$2-Model!K$2),Assumption!$F$16) -> 0 | M31: =MIN(L31+Assumption!$F$15*(Model!M$2-Model!L$2),Assumption!$F$16) -> 0 | N31: =MIN(M31+Assumption!$F$15*(Model!N$2-Model!M$2),Assumption!$F$16) -> 0 | O31: =MIN(N31+Assumption!$F$15*(Model!O$2-Model!N$2),Assumption!$F$16) -> 0 | ... BN31: =MIN(BM31+Assumption!$F$15*(Model!BN$2-Model!BM$2),Assumption!$F$16) -> 0
C32: Total | G32: =G26+G29 -> 275 | H32: =H26+H29 -> 140 | I32: =I26+I29 -> 140 | J32: =J26+J29 -> 140 | K32: =K26+K29 -> 140 | L32: =L26+L29 -> 140 | M32: =M26+M29 -> 140 | N32: =N26+N29 -> 140 | ... BN32: =BN26+BN29 -> 140
B34: 4 | C34: Daily order count (post-adjustment)
C35: On Mon - Thu | G35: =SUM(G36:G37) -> 1125 | H35: =SUM(H36:H37) -> 756 | I35: =SUM(I36:I37) -> 833 | J35: =SUM(J36:J37) -> 1008 | K35: =SUM(K36:K37) -> 1071 | L35: =SUM(L36:L37) -> 1190 | M35: =SUM(M36:M37) -> 1596 | N35: =SUM(N36:N37) -> 1120 | ... BN35: =SUM(BN36:BN37) -> 1190
C36: General seats | G36: =G27*SUM(G$10:G$13)*G$23 -> 1125 | H36: =H27*SUM(H$10:H$13)*H$23 -> 756 | I36: =I27*SUM(I$10:I$13)*I$23 -> 833 | J36: =J27*SUM(J$10:J$13)*J$23 -> 1008 | K36: =K27*SUM(K$10:K$13)*K$23 -> 1071 | L36: =L27*SUM(L$10:L$13)*L$23 -> 1190 | M36: =M27*SUM(M$10:M$13)*M$23 -> 1596 | N36: =N27*SUM(N$10:N$13)*N$23 -> 1120 | ... BN36: =BN27*SUM(BN$10:BN$13)*BN$23 -> 1190
C37: PDR | G37: =G28*SUM(G$14:G$16)*G$23 -> 0 | H37: =H28*SUM(H$14:H$16)*H$23 -> 0 | I37: =I28*SUM(I$14:I$16)*I$23 -> 0 | J37: =J28*SUM(J$14:J$16)*J$23 -> 0 | K37: =K28*SUM(K$14:K$16)*K$23 -> 0 | L37: =L28*SUM(L$14:L$16)*L$23 -> 0 | M37: =M28*SUM(M$14:M$16)*M$23 -> 0 | N37: =N28*SUM(N$14:N$16)*N$23 -> 0 | ... BN37: =BN28*SUM(BN$14:BN$16)*BN$23 -> 0
C38: On Fri - Sun | G38: =SUM(G39:G40) -> 1350 | H38: =SUM(H39:H40) -> 756 | I38: =SUM(I39:I40) -> 833 | J38: =SUM(J39:J40) -> 1008 | K38: =SUM(K39:K40) -> 1071 | L38: =SUM(L39:L40) -> 1190 | M38: =SUM(M39:M40) -> 1596 | N38: =SUM(N39:N40) -> 1120 | ... BN38: =SUM(BN39:BN40) -> 1190
C39: General seats | G39: =G30*SUM(G$10:G$13)*G$23 -> 1350 | H39: =H30*SUM(H$10:H$13)*H$23 -> 756 | I39: =I30*SUM(I$10:I$13)*I$23 -> 833 | J39: =J30*SUM(J$10:J$13)*J$23 -> 1008 | K39: =K30*SUM(K$10:K$13)*K$23 -> 1071 | L39: =L30*SUM(L$10:L$13)*L$23 -> 1190 | M39: =M30*SUM(M$10:M$13)*M$23 -> 1596 | N39: =N30*SUM(N$10:N$13)*N$23 -> 1120 | ... BN39: =BN30*SUM(BN$10:BN$13)*BN$23 -> 1190
C40: PDR | G40: =G31*SUM(G$14:G$16)*G$23 -> 0 | H40: =H31*SUM(H$14:H$16)*H$23 -> 0 | I40: =I31*SUM(I$14:I$16)*I$23 -> 0 | J40: =J31*SUM(J$14:J$16)*J$23 -> 0 | K40: =K31*SUM(K$14:K$16)*K$23 -> 0 | L40: =L31*SUM(L$14:L$16)*L$23 -> 0 | M40: =M31*SUM(M$14:M$16)*M$23 -> 0 | N40: =N31*SUM(N$14:N$16)*N$23 -> 0 | ... BN40: =BN31*SUM(BN$14:BN$16)*BN$23 -> 0
C41: Total | G41: =G35+G38 -> 2475 | H41: =H35+H38 -> 1512 | I41: =I35+I38 -> 1666 | J41: =J35+J38 -> 2016 | K41: =K35+K38 -> 2142 | L41: =L35+L38 -> 2380 | M41: =M35+M38 -> 3192 | N41: =N35+N38 -> 2240 | ... BN41: =BN35+BN38 -> 2380
C42: %Occupancy | G42: =G41/G$17/Assumption!$G$20 -> 1.1 | H42: =H41/H$17/Assumption!$G$20 -> 0.65032258 | I42: =I41/I$17/Assumption!$G$20 -> 0.71655914 | J42: =J41/J$17/Assumption!$G$20 -> 0.896 | K42: =K41/K$17/Assumption!$G$20 -> 0.92129032 | L42: =L41/L$17/Assumption!$G$20 -> 1.0577778 | M42: =M41/M$17/Assumption!$G$20 -> 1.3729032 | N42: =N41/N$17/Assumption!$G$20 -> 0.96344086 | ... BN42: =BN41/BN$17/Assumption!$G$20 -> 1.0236559
B44: 5 | C44: Revenue
C45: Total spending | G45: {=SUM(SUMPRODUCT(G36:G37,TRANSPOSE(Assumption!$E$5:$F$5)),SUMPRODUCT(G39:G40,TRANSPOSE(Assumption!$E$12:$F$12)))} -> 1170000000 | H45: {=SUM(SUMPRODUCT(H36:H37,TRANSPOSE(Assumption!$E$5:$F$5)),SUMPRODUCT(H39:H40,TRANSPOSE(Assumption!$E$12:$F$12)))*(1+(H2-G2)*Assumption!$G$21)} -> 680400000 | I45: {=SUM(SUMPRODUCT(I36:I37,TRANSPOSE(Assumption!$E$5:$F$5)),SUMPRODUCT(I39:I40,TRANSPOSE(Assumption!$E$12:$F$12)))*(1+(I2-H2)*Assumption!$G$21)} -> 749700000 | J45: {=SUM(SUMPRODUCT(J36:J37,TRANSPOSE(Assumption!$E$5:$F$5)),SUMPRODUCT(J39:J40,TRANSPOSE(Assumption!$E$12:$F$12)))*(1+(J2-I2)*Assumption!$G$21)} -> 907200000 | K45: {=SUM(SUMPRODUCT(K36:K37,TRANSPOSE(Assumption!$E$5:$F$5)),SUMPRODUCT(K39:K40,TRANSPOSE(Assumption!$E$12:$F$12)))*(1+(K2-J2)*Assumption!$G$21)} -> 963900000 | L45: {=SUM(SUMPRODUCT(L36:L37,TRANSPOSE(Assumption!$E$5:$F$5)),SUMPRODUCT(L39:L40,TRANSPOSE(Assumption!$E$12:$F$12)))*(1+(L2-K2)*Assumption!$G$21)} -> 1071000000 | M45: {=SUM(SUMPRODUCT(M36:M37,TRANSPOSE(Assumption!$E$5:$F$5)),SUMPRODUCT(M39:M40,TRANSPOSE(Assumption!$E$12:$F$12)))*(1+(M2-L2)*Assumption!$G$21)} -> 1436400000 | N45: {=SUM(SUMPRODUCT(N36:N37,TRANSPOSE(Assumption!$E$5:$F$5)),SUMPRODUCT(N39:N40,TRANSPOSE(Assumption!$E$12:$F$12)))*(1+(N2-M2)*Assumption!$G$21)} -> 1008000000 | O45: {=SUM(SUMPRODUCT(O36:O37,TRANSPOSE(Assumption!$E$5:$F$5)),SUMPRODUCT(O39:O40,TRANSPOSE(Assumption!$E$12:$F$12)))*(1+(O2-N2)*Assumption!$G$21)} -> 403200000 | ... BN45: {=SUM(SUMPRODUCT(BN36:BN37,TRANSPOSE(Assumption!$E$5:$F$5)),SUMPRODUCT(BN39:BN40,TRANSPOSE(Assumption!$E$12:$F$12)))*(1+(BN2-BM2)*Assumption!$G$21)} -> 1071000000
C46: Food spending | E46: 0.3 | G46: =G$45*$E46 -> 351000000 | H46: =H$45*$E46 -> 204120000 | I46: =I$45*$E46 -> 224910000 | J46: =J$45*$E46 -> 272160000 | K46: =K$45*$E46 -> 289170000 | L46: =L$45*$E46 -> 321300000 | M46: =M$45*$E46 -> 430920000 | N46: =N$45*$E46 -> 302400000 | ... BN46: =BN$45*$E46 -> 321300000
C47: Beverage spending | E47: 0.7 | G47: =G$45*$E47 -> 819000000 | H47: =H$45*$E47 -> 476280000 | I47: =I$45*$E47 -> 524790000 | J47: =J$45*$E47 -> 635040000 | K47: =K$45*$E47 -> 674730000 | L47: =L$45*$E47 -> 749700000 | M47: =M$45*$E47 -> 1005480000 | N47: =N$45*$E47 -> 705600000 | ... BN47: =BN$45*$E47 -> 749700000
C48: Service charge | E48: 0.05 | G48: =G45*$E$48 -> 58500000 | H48: =H45*$E$48 -> 34020000 | I48: =I45*$E$48 -> 37485000 | J48: =J45*$E$48 -> 45360000 | K48: =K45*$E$48 -> 48195000 | L48: =L45*$E$48 -> 53550000 | M48: =M45*$E$48 -> 71820000 | N48: =N45*$E$48 -> 50400000 | ... BN48: =BN45*$E$48 -> 53550000
C49: Gross revenue | G49: =G45+G48 -> 1228500000 | H49: =H45+H48 -> 714420000 | I49: =I45+I48 -> 787185000 | J49: =J45+J48 -> 952560000 | K49: =K45+K48 -> 1012095000 | L49: =L45+L48 -> 1124550000 | M49: =M45+M48 -> 1508220000 | N49: =N45+N48 -> 1058400000 | ... BN49: =BN45+BN48 -> 1124550000
C50: Defect | G50: =G46*Assumption!$G$28+Model!G47*Assumption!$G$29 -> 19890000 | H50: =H46*Assumption!$G$28+Model!H47*Assumption!$G$29 -> 11566800 | I50: =I46*Assumption!$G$28+Model!I47*Assumption!$G$29 -> 12744900 | J50: =J46*Assumption!$G$28+Model!J47*Assumption!$G$29 -> 15422400 | K50: =K46*Assumption!$G$28+Model!K47*Assumption!$G$29 -> 16386300 | L50: =L46*Assumption!$G$28+Model!L47*Assumption!$G$29 -> 18207000 | M50: =M46*Assumption!$G$28+Model!M47*Assumption!$G$29 -> 24418800 | N50: =N46*Assumption!$G$28+Model!N47*Assumption!$G$29 -> 17136000 | ... BN50: =BN46*Assumption!$G$28+Model!BN47*Assumption!$G$29 -> 18207000
B52: B | C52: COST STRUCTURE
B54: 1 | C54: COGS
C55: Food | G55: =G46*Assumption!$G31 -> 122850000 | H55: =H46*Assumption!$G31 -> 71442000 | I55: =I46*Assumption!$G31 -> 78718500 | J55: =J46*Assumption!$G31 -> 95256000 | K55: =K46*Assumption!$G31 -> 101209500 | L55: =L46*Assumption!$G31 -> 112455000 | M55: =M46*Assumption!$G31 -> 150822000 | N55: =N46*Assumption!$G31 -> 105840000 | ... BN55: =BN46*Assumption!$G31 -> 112455000
C56: Beverage | G56: =G47*Assumption!$G32 -> 212940000 | H56: =H47*Assumption!$G32 -> 123832800 | I56: =I47*Assumption!$G32 -> 136445400 | J56: =J47*Assumption!$G32 -> 165110400 | K56: =K47*Assumption!$G32 -> 175429800 | L56: =L47*Assumption!$G32 -> 194922000 | M56: =M47*Assumption!$G32 -> 261424800 | N56: =N47*Assumption!$G32 -> 183456000 | ... BN56: =BN47*Assumption!$G32 -> 194922000
C57: Total | G57: =SUM(G55:G56) -> 335790000 | H57: =SUM(H55:H56) -> 195274800 | I57: =SUM(I55:I56) -> 215163900 | J57: =SUM(J55:J56) -> 260366400 | K57: =SUM(K55:K56) -> 276639300 | L57: =SUM(L55:L56) -> 307377000 | M57: =SUM(M55:M56) -> 412246800 | N57: =SUM(N55:N56) -> 289296000 | ... BN57: =SUM(BN55:BN56) -> 307377000
B59: 2 | C59: Fixed costs
C60: Labor expenses | G60: =$O$154 -> 3.1732085e+08 | H60: =$O$154 -> 3.1732085e+08 | I60: =$O$154 -> 3.1732085e+08 | J60: =$O$154 -> 3.1732085e+08 | K60: =$O$154 -> 3.1732085e+08 | L60: =$O$154 -> 3.1732085e+08 | M60: =$O$154 -> 3.1732085e+08 | N60: =$O$154 -> 3.1732085e+08 | ... BN60: =$O$154 -> 3.1732085e+08
C61: Rental expenses | G61: =Assumption!G34 -> 75000000 | H61: =IF(MOD(H2-1,2)=0,Assumption!$G$34*(1+Assumption!$G$35)^((Model!H2-1)/2),Model!G61) -> 75000000 | I61: =IF(MOD(I2-1,2)=0,Assumption!$G$34*(1+Assumption!$G$35)^((Model!I2-1)/2),Model!H61) -> 75000000 | J61: =IF(MOD(J2-1,2)=0,Assumption!$G$34*(1+Assumption!$G$35)^((Model!J2-1)/2),Model!I61) -> 75000000 | K61: =IF(MOD(K2-1,2)=0,Assumption!$G$34*(1+Assumption!$G$35)^((Model!K2-1)/2),Model!J61) -> 75000000 | L61: =IF(MOD(L2-1,2)=0,Assumption!$G$34*(1+Assumption!$G$35)^((Model!L2-1)/2),Model!K61) -> 75000000 | M61: =IF(MOD(M2-1,2)=0,Assumption!$G$34*(1+Assumption!$G$35)^((Model!M2-1)/2),Model!L61) -> 75000000 | N61: =IF(MOD(N2-1,2)=0,Assumption!$G$34*(1+Assumption!$G$35)^((Model!N2-1)/2),Model!M61) -> 75000000 | O61: =IF(MOD(O2-1,2)=0,Assumption!$G$34*(1+Assumption!$G$35)^((Model!O2-1)/2),Model!N61) -> 75000000 | ... BN61: =IF(MOD(BN2-1,2)=0,Assumption!$G$34*(1+Assumption!$G$35)^((Model!BN2-1)/2),Model!BM61) -> 87480000
C62: Scent & Music Subscriptions | G62: =Assumption!$G$37 -> 1000000 | H62: =Assumption!$G$37 -> 1000000 | I62: =Assumption!$G$37 -> 1000000 | J62: =Assumption!$G$37 -> 1000000 | K62: =Assumption!$G$37 -> 1000000 | L62: =Assumption!$G$37 -> 1000000 | M62: =Assumption!$G$37 -> 1000000 | N62: =Assumption!$G$37 -> 1000000 | ... BN62: =Assumption!$G$37 -> 1000000
C63: Total | G63: =SUM(G60:G62) -> 3.9332085e+08 | H63: =SUM(H60:H62) -> 3.9332085e+08 | I63: =SUM(I60:I62) -> 3.9332085e+08 | J63: =SUM(J60:J62) -> 3.9332085e+08 | K63: =SUM(K60:K62) -> 3.9332085e+08 | L63: =SUM(L60:L62) -> 3.9332085e+08 | M63: =SUM(M60:M62) -> 3.9332085e+08 | N63: =SUM(N60:N62) -> 3.9332085e+08 | ... BN63: =SUM(BN60:BN62) -> 4.0580085e+08
B65: 3 | C65: Other fixed costs
C66: Take away set | G66: =Assumption!G39 -> 10000000 | H66: =G66*(1+Assumption!$G$46*(Model!H$2-Model!G$2)) -> 10000000 | I66: =H66*(1+Assumption!$G$46*(Model!I$2-Model!H$2)) -> 10000000 | J66: =I66*(1+Assumption!$G$46*(Model!J$2-Model!I$2)) -> 10000000 | K66: =J66*(1+Assumption!$G$46*(Model!K$2-Model!J$2)) -> 10000000 | L66: =K66*(1+Assumption!$G$46*(Model!L$2-Model!K$2)) -> 10000000 | M66: =L66*(1+Assumption!$G$46*(Model!M$2-Model!L$2)) -> 10000000 | N66: =M66*(1+Assumption!$G$46*(Model!N$2-Model!M$2)) -> 10000000 | O66: =N66*(1+Assumption!$G$46*(Model!O$2-Model!N$2)) -> 10000000 | ... BN66: =BM66*(1+Assumption!$G$46*(Model!BN$2-Model!BM$2)) -> 11698586
C67: MKT fee and Printing | G67: =Assumption!G40 -> 5000000 | H67: =G67*(1+Assumption!$G$46*(Model!H$2-Model!G$2)) -> 5000000 | I67: =H67*(1+Assumption!$G$46*(Model!I$2-Model!H$2)) -> 5000000 | J67: =I67*(1+Assumption!$G$46*(Model!J$2-Model!I$2)) -> 5000000 | K67: =J67*(1+Assumption!$G$46*(Model!K$2-Model!J$2)) -> 5000000 | L67: =K67*(1+Assumption!$G$46*(Model!L$2-Model!K$2)) -> 5000000 | M67: =L67*(1+Assumption!$G$46*(Model!M$2-Model!L$2)) -> 5000000 | N67: =M67*(1+Assumption!$G$46*(Model!N$2-Model!M$2)) -> 5000000 | O67: =N67*(1+Assumption!$G$46*(Model!O$2-Model!N$2)) -> 5000000 | ... BN67: =BM67*(1+Assumption!$G$46*(Model!BN$2-Model!BM$2)) -> 5849292.8
C68: Electricity & water expense | G68: =Assumption!G41 -> 30000000 | H68: =G68*(1+Assumption!$G$46*(Model!H$2-Model!G$2)) -> 30000000 | I68: =H68*(1+Assumption!$G$46*(Model!I$2-Model!H$2)) -> 30000000 | J68: =I68*(1+Assumption!$G$46*(Model!J$2-Model!I$2)) -> 30000000 | K68: =J68*(1+Assumption!$G$46*(Model!K$2-Model!J$2)) -> 30000000 | L68: =K68*(1+Assumption!$G$46*(Model!L$2-Model!K$2)) -> 30000000 | M68: =L68*(1+Assumption!$G$46*(Model!M$2-Model!L$2)) -> 30000000 | N68: =M68*(1+Assumption!$G$46*(Model!N$2-Model!M$2)) -> 30000000 | O68: =N68*(1+Assumption!$G$46*(Model!O$2-Model!N$2)) -> 30000000 | ... BN68: =BM68*(1+Assumption!$G$46*(Model!BN$2-Model!BM$2)) -> 35095757
C69: Internet & waste mgmt expense | G69: =Assumption!G42 -> 5000000 | H69: =G69*(1+Assumption!$G$46*(Model!H$2-Model!G$2)) -> 5000000 | I69: =H69*(1+Assumption!$G$46*(Model!I$2-Model!H$2)) -> 5000000 | J69: =I69*(1+Assumption!$G$46*(Model!J$2-Model!I$2)) -> 5000000 | K69: =J69*(1+Assumption!$G$46*(Model!K$2-Model!J$2)) -> 5000000 | L69: =K69*(1+Assumption!$G$46*(Model!L$2-Model!K$2)) -> 5000000 | M69: =L69*(1+Assumption!$G$46*(Model!M$2-Model!L$2)) -> 5000000 | N69: =M69*(1+Assumption!$G$46*(Model!N$2-Model!M$2)) -> 5000000 | O69: =N69*(1+Assumption!$G$46*(Model!O$2-Model!N$2)) -> 5000000 | ... BN69: =BM69*(1+Assumption!$G$46*(Model!BN$2-Model!BM$2)) -> 5849292.8
C70: Monthly maintenance expense | G70: =Assumption!G43 -> 10000000 | H70: =G70*(1+Assumption!$G$46*(Model!H$2-Model!G$2)) -> 10000000 | I70: =H70*(1+Assumption!$G$46*(Model!I$2-Model!H$2)) -> 10000000 | J70: =I70*(1+Assumption!$G$46*(Model!J$2-Model!I$2)) -> 10000000 | K70: =J70*(1+Assumption!$G$46*(Model!K$2-Model!J$2)) -> 10000000 | L70: =K70*(1+Assumption!$G$46*(Model!L$2-Model!K$2)) -> 10000000 | M70: =L70*(1+Assumption!$G$46*(Model!M$2-Model!L$2)) -> 10000000 | N70: =M70*(1+Assumption!$G$46*(Model!N$2-Model!M$2)) -> 10000000 | O70: =N70*(1+Assumption!$G$46*(Model!O$2-Model!N$2)) -> 10000000 | ... BN70: =BM70*(1+Assumption!$G$46*(Model!BN$2-Model!BM$2)) -> 11698586
C71: Parking expense | G71: =Assumption!G44 -> 5000000 | H71: =G71*(1+Assumption!$G$46*(Model!H$2-Model!G$2)) -> 5000000 | I71: =H71*(1+Assumption!$G$46*(Model!I$2-Model!H$2)) -> 5000000 | J71: =I71*(1+Assumption!$G$46*(Model!J$2-Model!I$2)) -> 5000000 | K71: =J71*(1+Assumption!$G$46*(Model!K$2-Model!J$2)) -> 5000000 | L71: =K71*(1+Assumption!$G$46*(Model!L$2-Model!K$2)) -> 5000000 | M71: =L71*(1+Assumption!$G$46*(Model!M$2-Model!L$2)) -> 5000000 | N71: =M71*(1+Assumption!$G$46*(Model!N$2-Model!M$2)) -> 5000000 | O71: =N71*(1+Assumption!$G$46*(Model!O$2-Model!N$2)) -> 5000000 | ... BN71: =BM71*(1+Assumption!$G$46*(Model!BN$2-Model!BM$2)) -> 5849292.8
C72: Contingency | G72: =Assumption!G45 -> 10000000 | H72: =G72*(1+Assumption!$G$46*(Model!H$2-Model!G$2)) -> 10000000 | I72: =H72*(1+Assumption!$G$46*(Model!I$2-Model!H$2)) -> 10000000 | J72: =I72*(1+Assumption!$G$46*(Model!J$2-Model!I$2)) -> 10000000 | K72: =J72*(1+Assumption!$G$46*(Model!K$2-Model!J$2)) -> 10000000 | L72: =K72*(1+Assumption!$G$46*(Model!L$2-Model!K$2)) -> 10000000 | M72: =L72*(1+Assumption!$G$46*(Model!M$2-Model!L$2)) -> 10000000 | N72: =M72*(1+Assumption!$G$46*(Model!N$2-Model!M$2)) -> 10000000 | O72: =N72*(1+Assumption!$G$46*(Model!O$2-Model!N$2)) -> 10000000 | ... BN72: =BM72*(1+Assumption!$G$46*(Model!BN$2-Model!BM$2)) -> 11698586
C73: Total | G73: =SUM(G66:G72) -> 75000000 | H73: =SUM(H66:H72) -> 75000000 | I73: =SUM(I66:I72) -> 75000000 | J73: =SUM(J66:J72) -> 75000000 | K73: =SUM(K66:K72) -> 75000000 | L73: =SUM(L66:L72) -> 75000000 | M73: =SUM(M66:M72) -> 75000000 | N73: =SUM(N66:N72) -> 75000000 | ... BN73: =SUM(BN66:BN72) -> 87739392
B75: 4 | C75: Variable costs
C76: G&A expenses | G76: =G$45*Assumption!$G50 -> 58500000 | H76: =H$45*Assumption!$G50 -> 34020000 | I76: =I$45*Assumption!$G50 -> 37485000 | J76: =J$45*Assumption!$G50 -> 45360000 | K76: =K$45*Assumption!$G50 -> 48195000 | L76: =L$45*Assumption!$G50 -> 53550000 | M76: =M$45*Assumption!$G50 -> 71820000 | N76: =N$45*Assumption!$G50 -> 50400000 | ... BN76: =BN$45*Assumption!$G50 -> 53550000
C77: Marketing expenses | G77: =G$45*Assumption!$G51 -> 11700000 | H77: =H$45*Assumption!$G51 -> 6804000 | I77: =I$45*Assumption!$G51 -> 7497000 | J77: =J$45*Assumption!$G51 -> 9072000 | K77: =K$45*Assumption!$G51 -> 9639000 | L77: =L$45*Assumption!$G51 -> 10710000 | M77: =M$45*Assumption!$G51 -> 14364000 | N77: =N$45*Assumption!$G51 -> 10080000 | ... BN77: =BN$45*Assumption!$G51 -> 10710000
C78: Total | G78: =SUM(G76:G77) -> 70200000 | H78: =SUM(H76:H77) -> 40824000 | I78: =SUM(I76:I77) -> 44982000 | J78: =SUM(J76:J77) -> 54432000 | K78: =SUM(K76:K77) -> 57834000 | L78: =SUM(L76:L77) -> 64260000 | M78: =SUM(M76:M77) -> 86184000 | N78: =SUM(N76:N77) -> 60480000 | ... BN78: =SUM(BN76:BN77) -> 64260000
B80: 5 | C80: Debt schedule | E80: 0
B82: 6 | C82: D&A schedule (Initial capex)
C83: Fixed asset, OB | E83: =Capex!E31 -> 4061841703 | G83: =E83 -> 4061841703 | H83: =G85 -> 3994144341 | I83: =H85 -> 3926446979 | J83: =I85 -> 3858749617 | K83: =J85 -> 3791052256 | L83: =K85 -> 3723354894 | M83: =L85 -> 3655657532 | N83: =M85 -> 3587960171 | O83: =N85 -> 3520262809 | ... BN83: =BM85 -> 67697362
C84: D&A expense | E84: 5 | G84: =MIN(G83,$E83/$E84/12) -> 67697362 | H84: =MIN(H83,$E83/$E84/12) -> 67697362 | I84: =MIN(I83,$E83/$E84/12) -> 67697362 | J84: =MIN(J83,$E83/$E84/12) -> 67697362 | K84: =MIN(K83,$E83/$E84/12) -> 67697362 | L84: =MIN(L83,$E83/$E84/12) -> 67697362 | M84: =MIN(M83,$E83/$E84/12) -> 67697362 | N84: =MIN(N83,$E83/$E84/12) -> 67697362 | ... BN84: =MIN(BN83,$E83/$E84/12) -> 67697362
C85: Fixed asset, EB | G85: =G83-G84 -> 3994144341 | H85: =H83-H84 -> 3926446979 | I85: =I83-I84 -> 3858749617 | J85: =J83-J84 -> 3791052256 | K85: =K83-K84 -> 3723354894 | L85: =L83-L84 -> 3655657532 | M85: =M83-M84 -> 3587960171 | N85: =N83-N84 -> 3520262809 | ... BN85: =BN83-BN84 -> 4.3213367e-06
B87: 7 | C87: D&A schedule (FY1)
C88: Fixed asset, OB | E88: =Capex!E33 -> 0 | S88: =E88 -> 0 | T88: =S90 -> 0 | U88: =T90 -> 0 | V88: =U90 -> 0 | W88: =V90 -> 0 | X88: =W90 -> 0 | Y88: =X90 -> 0 | Z88: =Y90 -> 0 | AA88: =Z90 -> 0 | ... BN88: =BM90 -> 0
C89: D&A expense | E89: 3 | S89: =MIN(S88,$E88/$E89/12) -> 0 | T89: =MIN(T88,$E88/$E89/12) -> 0 | U89: =MIN(U88,$E88/$E89/12) -> 0 | V89: =MIN(V88,$E88/$E89/12) -> 0 | W89: =MIN(W88,$E88/$E89/12) -> 0 | X89: =MIN(X88,$E88/$E89/12) -> 0 | Y89: =MIN(Y88,$E88/$E89/12) -> 0 | Z89: =MIN(Z88,$E88/$E89/12) -> 0 | ... BN89: =MIN(BN88,$E88/$E89/12) -> 0
C90: Fixed asset, EB | S90: =S88-S89 -> 0 | T90: =T88-T89 -> 0 | U90: =U88-U89 -> 0 | V90: =V88-V89 -> 0 | W90: =W88-W89 -> 0 | X90: =X88-X89 -> 0 | Y90: =Y88-Y89 -> 0 | Z90: =Z88-Z89 -> 0 | ... BN90: =BN88-BN89 -> 0
B92: 8 | C92: D&A schedule (FY2)
C93: Fixed asset, OB | E93: =Capex!E34 | AE93: =E93 | AF93: =AE95 -> 0 | AG93: =AF95 -> 0 | AH93: =AG95 -> 0 | AI93: =AH95 -> 0 | AJ93: =AI95 -> 0 | AK93: =AJ95 -> 0 | AL93: =AK95 -> 0 | AM93: =AL95 -> 0 | ... BN93: =BM95 -> 0
C94: D&A expense | E94: 3 | AE94: =MIN(AE93,$E93/$E94/12) -> 0 | AF94: =MIN(AF93,$E93/$E94/12) -> 0 | AG94: =MIN(AG93,$E93/$E94/12) -> 0 | AH94: =MIN(AH93,$E93/$E94/12) -> 0 | AI94: =MIN(AI93,$E93/$E94/12) -> 0 | AJ94: =MIN(AJ93,$E93/$E94/12) -> 0 | AK94: =MIN(AK93,$E93/$E94/12) -> 0 | AL94: =MIN(AL93,$E93/$E94/12) -> 0 | ... BN94: =MIN(BN93,$E93/$E94/12) -> 0
C95: Fixed asset, EB | AE95: =AE93-AE94 -> 0 | AF95: =AF93-AF94 -> 0 | AG95: =AG93-AG94 -> 0 | AH95: =AH93-AH94 -> 0 | AI95: =AI93-AI94 -> 0 | AJ95: =AJ93-AJ94 -> 0 | AK95: =AK93-AK94 -> 0 | AL95: =AL93-AL94 -> 0 | ... BN95: =BN93-BN94 -> 0
B97: 9 | C97: D&A schedule (FY3)
C98: Fixed asset, OB | E98: =Capex!E35 | AQ98: =E98 | AR98: =AQ100 -> 0 | AS98: =AR100 -> 0 | AT98: =AS100 -> 0 | AU98: =AT100 -> 0 | AV98: =AU100 -> 0 | AW98: =AV100 -> 0 | AX98: =AW100 -> 0 | AY98: =AX100 -> 0 | ... BN98: =BM100 -> 0
C99: D&A expense | E99: 3 | AQ99: =MIN(AQ98,$E98/$E99/12) -> 0 | AR99: =MIN(AR98,$E98/$E99/12) -> 0 | AS99: =MIN(AS98,$E98/$E99/12) -> 0 | AT99: =MIN(AT98,$E98/$E99/12) -> 0 | AU99: =MIN(AU98,$E98/$E99/12) -> 0 | AV99: =MIN(AV98,$E98/$E99/12) -> 0 | AW99: =MIN(AW98,$E98/$E99/12) -> 0 | AX99: =MIN(AX98,$E98/$E99/12) -> 0 | ... BN99: =MIN(BN98,$E98/$E99/12) -> 0
C100: Fixed asset, EB | AQ100: =AQ98-AQ99 -> 0 | AR100: =AR98-AR99 -> 0 | AS100: =AS98-AS99 -> 0 | AT100: =AT98-AT99 -> 0 | AU100: =AU98-AU99 -> 0 | AV100: =AV98-AV99 -> 0 | AW100: =AW98-AW99 -> 0 | AX100: =AX98-AX99 -> 0 | ... BN100: =BN98-BN99 -> 0
B102: 10 | C102: D&A schedule (FY4)
C103: Fixed asset, OB | E103: =Capex!E36 | BC103: =E103 | BD103: =BC105 -> 0 | BE103: =BD105 -> 0 | BF103: =BE105 -> 0 | BG103: =BF105 -> 0 | BH103: =BG105 -> 0 | BI103: =BH105 -> 0 | BJ103: =BI105 -> 0 | BK103: =BJ105 -> 0 | ... BN103: =BM105 -> 0
C104: D&A expense | E104: 3 | BC104: =MIN(BC103,$E103/$E104/12) -> 0 | BD104: =MIN(BD103,$E103/$E104/12) -> 0 | BE104: =MIN(BE103,$E103/$E104/12) -> 0 | BF104: =MIN(BF103,$E103/$E104/12) -> 0 | BG104: =MIN(BG103,$E103/$E104/12) -> 0 | BH104: =MIN(BH103,$E103/$E104/12) -> 0 | BI104: =MIN(BI103,$E103/$E104/12) -> 0 | BJ104: =MIN(BJ103,$E103/$E104/12) -> 0 | ... BN104: =MIN(BN103,$E103/$E104/12) -> 0
C105: Fixed asset, EB | BC105: =BC103-BC104 -> 0 | BD105: =BD103-BD104 -> 0 | BE105: =BE103-BE104 -> 0 | BF105: =BF103-BF104 -> 0 | BG105: =BG103-BG104 -> 0 | BH105: =BH103-BH104 -> 0 | BI105: =BI103-BI104 -> 0 | BJ105: =BJ103-BJ104 -> 0 | ... BN105: =BN103-BN104 -> 0
B107: C | C107: PRO-FORMA P&L
C109: Gross revenue | G109: =G49 -> 1228500000 | H109: =H49 -> 714420000 | I109: =I49 -> 787185000 | J109: =J49 -> 952560000 | K109: =K49 -> 1012095000 | L109: =L49 -> 1124550000 | M109: =M49 -> 1508220000 | N109: =N49 -> 1058400000 | ... BN109: =BN49 -> 1124550000
C110: Defect | G110: =G50 -> 19890000 | H110: =H50 -> 11566800 | I110: =I50 -> 12744900 | J110: =J50 -> 15422400 | K110: =K50 -> 16386300 | L110: =L50 -> 18207000 | M110: =M50 -> 24418800 | N110: =N50 -> 17136000 | ... BN110: =BN50 -> 18207000
C111: Net revenue | G111: =G109-G110 -> 1208610000 | H111: =H109-H110 -> 702853200 | I111: =I109-I110 -> 774440100 | J111: =J109-J110 -> 937137600 | K111: =K109-K110 -> 995708700 | L111: =L109-L110 -> 1106343000 | M111: =M109-M110 -> 1483801200 | N111: =N109-N110 -> 1041264000 | ... BN111: =BN109-BN110 -> 1106343000
C112: COGS | G112: =G57 -> 335790000 | H112: =H57 -> 195274800 | I112: =I57 -> 215163900 | J112: =J57 -> 260366400 | K112: =K57 -> 276639300 | L112: =L57 -> 307377000 | M112: =M57 -> 412246800 | N112: =N57 -> 289296000 | ... BN112: =BN57 -> 307377000
C113: Gross profit | G113: =G111-G112 -> 872820000 | H113: =H111-H112 -> 507578400 | I113: =I111-I112 -> 559276200 | J113: =J111-J112 -> 676771200 | K113: =K111-K112 -> 719069400 | L113: =L111-L112 -> 798966000 | M113: =M111-M112 -> 1071554400 | N113: =N111-N112 -> 751968000 | ... BN113: =BN111-BN112 -> 798966000
C114: Gross margin | G114: =G113/G$109 -> 0.71047619 | H114: =H113/H$109 -> 0.71047619 | I114: =I113/I$109 -> 0.71047619 | J114: =J113/J$109 -> 0.71047619 | K114: =K113/K$109 -> 0.71047619 | L114: =L113/L$109 -> 0.71047619 | M114: =M113/M$109 -> 0.71047619 | N114: =N113/N$109 -> 0.71047619 | ... BN114: =BN113/BN$109 -> 0.71047619
C115: Labor expenses | G115: =G60 -> 3.1732085e+08 | H115: =H60 -> 3.1732085e+08 | I115: =I60 -> 3.1732085e+08 | J115: =J60 -> 3.1732085e+08 | K115: =K60 -> 3.1732085e+08 | L115: =L60 -> 3.1732085e+08 | M115: =M60 -> 3.1732085e+08 | N115: =N60 -> 3.1732085e+08 | ... BN115: =BN60 -> 3.1732085e+08
C116: Rental expenses | G116: =G61 -> 75000000 | H116: =H61 -> 75000000 | I116: =I61 -> 75000000 | J116: =J61 -> 75000000 | K116: =K61 -> 75000000 | L116: =L61 -> 75000000 | M116: =M61 -> 75000000 | N116: =N61 -> 75000000 | ... BN116: =BN61 -> 87480000
C117: Other operation expenses | G117: =G73 -> 75000000 | H117: =H73 -> 75000000 | I117: =I73 -> 75000000 | J117: =J73 -> 75000000 | K117: =K73 -> 75000000 | L117: =L73 -> 75000000 | M117: =M73 -> 75000000 | N117: =N73 -> 75000000 | ... BN117: =BN73 -> 87739392
C118: G&A expenses | G118: =G76 -> 58500000 | H118: =H76 -> 34020000 | I118: =I76 -> 37485000 | J118: =J76 -> 45360000 | K118: =K76 -> 48195000 | L118: =L76 -> 53550000 | M118: =M76 -> 71820000 | N118: =N76 -> 50400000 | ... BN118: =BN76 -> 53550000
C119: Marketing expenses | G119: =G77 -> 11700000 | H119: =H77 -> 6804000 | I119: =I77 -> 7497000 | J119: =J77 -> 9072000 | K119: =K77 -> 9639000 | L119: =L77 -> 10710000 | M119: =M77 -> 14364000 | N119: =N77 -> 10080000 | ... BN119: =BN77 -> 10710000
...

Sheet Summary
B2: SUMMARY
B3: Year | D3: 1 | E3: =D3+1 -> 2 | F3: =E3+1 -> 3 | G3: =F3+1 -> 4 | H3: =G3+1 -> 5
B4: Begin Date | D4: =Model!G5 -> 46174 | E4: =D5+1 -> 46539 | F4: =E5+1 -> 46905 | G4: =F5+1 -> 47270 | H4: =G5+1 -> 47635
B5: End Date | D5: =EOMONTH(D4,11) -> 46538 | E5: =EOMONTH(E4,11) -> 46904 | F5: =EOMONTH(F4,11) -> 47269 | G5: =EOMONTH(G4,11) -> 47634 | H5: =EOMONTH(H4,11) -> 47999
B6: PRO-FORMA P&L:
B7: Gross revenue | C7: [VND] | D7: =SUMIFS(Model!$G109:$BN109,Model!$G$2:$BN$2,Summary!D$3) -> 12315240000 | E7: =SUMIFS(Model!$G109:$BN109,Model!$G$2:$BN$2,Summary!E$3) -> 13514445000 | F7: =SUMIFS(Model!$G109:$BN109,Model!$G$2:$BN$2,Summary!F$3) -> 13458217500 | G7: =SUMIFS(Model!$G109:$BN109,Model!$G$2:$BN$2,Summary!G$3) -> 13401990000 | H7: =SUMIFS(Model!$G109:$BN109,Model!$G$2:$BN$2,Summary!H$3) -> 13415220000
B8: Deduction | C8: [VND] | D8: =SUMIFS(Model!$G110:$BN110,Model!$G$2:$BN$2,Summary!D$3) -> 199389600 | E8: =SUMIFS(Model!$G110:$BN110,Model!$G$2:$BN$2,Summary!E$3) -> 218805300 | F8: =SUMIFS(Model!$G110:$BN110,Model!$G$2:$BN$2,Summary!F$3) -> 217894950 | G8: =SUMIFS(Model!$G110:$BN110,Model!$G$2:$BN$2,Summary!G$3) -> 216984600 | H8: =SUMIFS(Model!$G110:$BN110,Model!$G$2:$BN$2,Summary!H$3) -> 217198800
B9: Net revenue | C9: [VND] | D9: =D7-D8 -> 12115850400 | E9: =E7-E8 -> 13295639700 | F9: =F7-F8 -> 13240322550 | G9: =G7-G8 -> 13185005400 | H9: =H7-H8 -> 13198021200
B10: COGS | C10: [VND] | D10: =SUMIFS(Model!$G112:$BN112,Model!$G$2:$BN$2,Summary!D$3) -> 3366165600 | E10: =SUMIFS(Model!$G112:$BN112,Model!$G$2:$BN$2,Summary!E$3) -> 3693948300 | F10: =SUMIFS(Model!$G112:$BN112,Model!$G$2:$BN$2,Summary!F$3) -> 3678579450 | G10: =SUMIFS(Model!$G112:$BN112,Model!$G$2:$BN$2,Summary!G$3) -> 3663210600 | H10: =SUMIFS(Model!$G112:$BN112,Model!$G$2:$BN$2,Summary!H$3) -> 3666826800
B11: Gross profit | C11: [VND] | D11: =D9-D10 -> 8749684800 | E11: =E9-E10 -> 9601691400 | F11: =F9-F10 -> 9561743100 | G11: =G9-G10 -> 9521794800 | H11: =H9-H10 -> 9531194400
B12: Gross margin | C12: [%] | D12: =IFERROR(D11/D$7,0) -> 0.71047619 | E12: =IFERROR(E11/E$7,0) -> 0.71047619 | F12: =IFERROR(F11/F$7,0) -> 0.71047619 | G12: =IFERROR(G11/G$7,0) -> 0.71047619 | H12: =IFERROR(H11/H$7,0) -> 0.71047619
B13: Labor expenses | C13: [VND] | D13: =SUMIFS(Model!$G115:$BN115,Model!$G$2:$BN$2,Summary!D$3) -> 3807850215 | E13: =SUMIFS(Model!$G115:$BN115,Model!$G$2:$BN$2,Summary!E$3) -> 3807850215 | F13: =SUMIFS(Model!$G115:$BN115,Model!$G$2:$BN$2,Summary!F$3) -> 3807850215 | G13: =SUMIFS(Model!$G115:$BN115,Model!$G$2:$BN$2,Summary!G$3) -> 3807850215 | H13: =SUMIFS(Model!$G115:$BN115,Model!$G$2:$BN$2,Summary!H$3) -> 3807850215
B14: Rental expenses | C14: [VND] | D14: =SUMIFS(Model!$G116:$BN116,Model!$G$2:$BN$2,Summary!D$3) -> 900000000 | E14: =SUMIFS(Model!$G116:$BN116,Model!$G$2:$BN$2,Summary!E$3) -> 900000000 | F14: =SUMIFS(Model!$G116:$BN116,Model!$G$2:$BN$2,Summary!F$3) -> 972000000 | G14: =SUMIFS(Model!$G116:$BN116,Model!$G$2:$BN$2,Summary!G$3) -> 972000000 | H14: =SUMIFS(Model!$G116:$BN116,Model!$G$2:$BN$2,Summary!H$3) -> 1049760000
B15: Other operating expenses | C15: [VND] | D15: =SUMIFS(Model!$G117:$BN117,Model!$G$2:$BN$2,Summary!D$3) -> 900000000 | E15: =SUMIFS(Model!$G117:$BN117,Model!$G$2:$BN$2,Summary!E$3) -> 936000000 | F15: =SUMIFS(Model!$G117:$BN117,Model!$G$2:$BN$2,Summary!F$3) -> 973440000 | G15: =SUMIFS(Model!$G117:$BN117,Model!$G$2:$BN$2,Summary!G$3) -> 1012377600 | H15: =SUMIFS(Model!$G117:$BN117,Model!$G$2:$BN$2,Summary!H$3) -> 1052872704
B16: G&A expenses | C16: [VND] | D16: =SUMIFS(Model!$G118:$BN118,Model!$G$2:$BN$2,Summary!D$3) -> 586440000 | E16: =SUMIFS(Model!$G118:$BN118,Model!$G$2:$BN$2,Summary!E$3) -> 643545000 | F16: =SUMIFS(Model!$G118:$BN118,Model!$G$2:$BN$2,Summary!F$3) -> 640867500 | G16: =SUMIFS(Model!$G118:$BN118,Model!$G$2:$BN$2,Summary!G$3) -> 638190000 | H16: =SUMIFS(Model!$G118:$BN118,Model!$G$2:$BN$2,Summary!H$3) -> 638820000
B17: Marketing expenses | C17: [VND] | D17: =SUMIFS(Model!$G119:$BN119,Model!$G$2:$BN$2,Summary!D$3) -> 117288000 | E17: =SUMIFS(Model!$G119:$BN119,Model!$G$2:$BN$2,Summary!E$3) -> 128709000 | F17: =SUMIFS(Model!$G119:$BN119,Model!$G$2:$BN$2,Summary!F$3) -> 128173500 | G17: =SUMIFS(Model!$G119:$BN119,Model!$G$2:$BN$2,Summary!G$3) -> 127638000 | H17: =SUMIFS(Model!$G119:$BN119,Model!$G$2:$BN$2,Summary!H$3) -> 127764000
B18: EBITDA | C18: [VND] | D18: =D11-SUM(D13:D17) -> 2438106585 | E18: =E11-SUM(E13:E17) -> 3185587185 | F18: =F11-SUM(F13:F17) -> 3039411885 | G18: =G11-SUM(G13:G17) -> 2963738985 | H18: =H11-SUM(H13:H17) -> 2854127481
B19: EBITDA margin | C19: [%] | D19: =IFERROR(D18/D$7,0) -> 0.19797475 | E19: =IFERROR(E18/E$7,0) -> 0.2357172 | F19: =IFERROR(F18/F$7,0) -> 0.2258406 | G19: =IFERROR(G18/G$7,0) -> 0.22114171 | H19: =IFERROR(H18/H$7,0) -> 0.21275294
B20: D&A expense | C20: [VND] | D20: =SUMIFS(Model!$G122:$BN122,Model!$G$2:$BN$2,Summary!D$3) -> 8.1236834e+08 | E20: =SUMIFS(Model!$G122:$BN122,Model!$G$2:$BN$2,Summary!E$3) -> 8.1236834e+08 | F20: =SUMIFS(Model!$G122:$BN122,Model!$G$2:$BN$2,Summary!F$3) -> 8.1236834e+08 | G20: =SUMIFS(Model!$G122:$BN122,Model!$G$2:$BN$2,Summary!G$3) -> 8.1236834e+08 | H20: =SUMIFS(Model!$G122:$BN122,Model!$G$2:$BN$2,Summary!H$3) -> 8.1236834e+08
B21: EBIT | C21: [VND] | D21: =D18-D20 -> 1625738244 | E21: =E18-E20 -> 2373218844 | F21: =F18-F20 -> 2227043544 | G21: =G18-G20 -> 2151370644 | H21: =H18-H20 -> 2041759140
B22: EBIT margin | C22: [%] | D22: =IFERROR(D21/D$7,0) -> 0.13201028 | E22: =IFERROR(E21/E$7,0) -> 0.17560609 | F22: =IFERROR(F21/F$7,0) -> 0.16547834 | G22: =IFERROR(G21/G$7,0) -> 0.16052621 | H22: =IFERROR(H21/H$7,0) -> 0.15219722
B23: Interest expense | C23: [VND] | D23: =SUMIFS(Model!$G125:$BN125,Model!$G$2:$BN$2,Summary!D$3) -> 0 | E23: =SUMIFS(Model!$G125:$BN125,Model!$G$2:$BN$2,Summary!E$3) -> 0 | F23: =SUMIFS(Model!$G125:$BN125,Model!$G$2:$BN$2,Summary!F$3) -> 0 | G23: =SUMIFS(Model!$G125:$BN125,Model!$G$2:$BN$2,Summary!G$3) -> 0 | H23: =SUMIFS(Model!$G125:$BN125,Model!$G$2:$BN$2,Summary!H$3) -> 0
B24: EBT | C24: [VND] | D24: =D21-D23 -> 1625738244 | E24: =E21-E23 -> 2373218844 | F24: =F21-F23 -> 2227043544 | G24: =G21-G23 -> 2151370644 | H24: =H21-H23 -> 2041759140
B25: EBT margin | C25: [%] | D25: =IFERROR(D24/D$7,0) -> 0.13201028 | E25: =IFERROR(E24/E$7,0) -> 0.17560609 | F25: =IFERROR(F24/F$7,0) -> 0.16547834 | G25: =IFERROR(G24/G$7,0) -> 0.16052621 | H25: =IFERROR(H24/H$7,0) -> 0.15219722
B26: Cumulative | C26: [VND] | D26: =D24 -> 1625738244 | E26: =D26+E24 -> 3998957088 | F26: =E26+F24 -> 6226000632 | G26: =F26+G24 -> 8377371276 | H26: =G26+H24 -> 10419130417
B27: CIT | C27: [VND] | D27: =IF(OR(D24<0,D26<0),0,MIN(D24,D26)*20%) -> 3.2514765e+08 | E27: =IF(OR(E24<0,E26<0),0,MIN(E24,E26)*20%) -> 4.7464377e+08 | F27: =IF(OR(F24<0,F26<0),0,MIN(F24,F26)*20%) -> 4.4540871e+08 | G27: =IF(OR(G24<0,G26<0),0,MIN(G24,G26)*20%) -> 4.3027413e+08 | H27: =IF(OR(H24<0,H26<0),0,MIN(H24,H26)*20%) -> 408351828
B28: NPAT | C28: [VND] | D28: =D24-D27 -> 1300590595 | E28: =E24-E27 -> 1898575075 | F28: =F24-F27 -> 1781634835 | G28: =G24-G27 -> 1721096515 | H28: =H24-H27 -> 1633407312
B29: Net margin | C29: [%] | D29: =IFERROR(D28/D$7,0) -> 0.10560822 | E29: =IFERROR(E28/E$7,0) -> 0.14048487 | F29: =IFERROR(F28/F$7,0) -> 0.13238268 | G29: =IFERROR(G28/G$7,0) -> 0.12842097 | H29: =IFERROR(H28/H$7,0) -> 0.12175777
B32: KPI:
B33: Daily seat occupied | C33: [seat] | D33: =SUMIFS(Model!G41:BN41,Model!G2:BN2,Summary!D3)/SUMIFS(Model!G17:BN17,Model!G2:BN2,Summary!D3) -> 71.065753 | E33: =SUMIFS(Model!H41:BP41,Model!H2:BP2,Summary!E3)/SUMIFS(Model!H17:BP17,Model!H2:BP2,Summary!E3) -> 77.803279 | F33: =SUMIFS(Model!I41:BQ41,Model!I2:BQ2,Summary!F3)/SUMIFS(Model!I17:BQ17,Model!I2:BQ2,Summary!F3) -> 77.709589 | G33: =SUMIFS(Model!J41:BR41,Model!J2:BR2,Summary!G3)/SUMIFS(Model!J17:BR17,Model!J2:BR2,Summary!G3) -> 77.40274 | H33: =SUMIFS(Model!K41:BS41,Model!K2:BS2,Summary!H3)/SUMIFS(Model!K17:BS17,Model!K2:BS2,Summary!H3) -> 77.479452
B34: Occupancy rate | C34: [%] | D34: =D33/Assumption!$G$20 -> 0.94754338 | E34: =E33/Assumption!$G$20 -> 1.037377 | F34: =F33/Assumption!$G$20 -> 1.0361279 | G34: =G33/Assumption!$G$20 -> 1.0320365 | H34: =H33/Assumption!$G$20 -> 1.0330594
B35: Average spending | C35: [VND] | D35: =D7/SUMIFS(Model!G41:BN41,Model!G2:BN2,Summary!D3) -> 474776.98 | E35: =E7/SUMIFS(Model!H41:BP41,Model!H2:BP2,Summary!E3) -> 474590.71 | F35: =F7/SUMIFS(Model!I41:BQ41,Model!I2:BQ2,Summary!F3) -> 474482.35 | G35: =G7/SUMIFS(Model!J41:BR41,Model!J2:BR2,Summary!G3) -> 474373.14 | H35: =H7/SUMIFS(Model!K41:BS41,Model!K2:BS2,Summary!H3) -> 474371.29
B36: Revenue growth | C36: [%] | E36: =E7/D7-1 -> 0.097375691 | F36: =F7/E7-1 -> -0.0041605482 | G36: =G7/F7-1 -> -0.0041779307 | H36: =H7/G7-1 -> 0.00098716683

Sheet 4. Cashflow
B2: Initial capital requirement (Sep/25): | E2: =F55 -> 4061841703 | F2: Tháng đầu tiên đang gánh thêm working capital của 2 tháng đầu.
B4: Total equity requirement in Sep/25 - Feb/26: | E4: =SUM(D36:I36) -> -2329175908 | F4: Nhỏ hơn tổng mức đầu tư ban đầu do có doanh thu hoạt động gánh cùng.
B6: Cash flow | D6: 46174 | E6: =EOMONTH(D6,1) -> 46234 | F6: =EOMONTH(E6,1) -> 46265 | G6: =EOMONTH(F6,1) -> 46295 | H6: =EOMONTH(G6,1) -> 46326 | I6: =EOMONTH(H6,1) -> 46356
B7: 1 | C7: Cashflow from operation
C8: Net revenue | D8: =Model!G111 -> 1208610000 | E8: =Model!H111 -> 702853200 | F8: =Model!I111 -> 774440100 | G8: =Model!J111 -> 937137600 | H8: =Model!K111 -> 995708700 | I8: =Model!L111 -> 1106343000
C9: COGS | D9: =-Model!G112 -> -335790000 | E9: =-Model!H112 -> -195274800 | F9: =-Model!I112 -> -215163900 | G9: =-Model!J112 -> -260366400 | H9: =-Model!K112 -> -276639300 | I9: =-Model!L112 -> -307377000
C10: Labor expenses | D10: =-Model!G115 -> -3.1732085e+08 | E10: =-Model!H115 -> -3.1732085e+08 | F10: =-Model!I115 -> -3.1732085e+08 | G10: =-Model!J115 -> -3.1732085e+08 | H10: =-Model!K115 -> -3.1732085e+08 | I10: =-Model!L115 -> -3.1732085e+08
C11: Rental expenses | D11: =-Model!G116 -> -75000000 | E11: =-Model!H116 -> -75000000 | F11: =-Model!I116 -> -75000000 | G11: =-Model!J116 -> -75000000 | H11: =-Model!K116 -> -75000000 | I11: =-Model!L116 -> -75000000
C12: Other operating expenses | D12: =-Model!G117 -> -75000000 | E12: =-Model!H117 -> -75000000 | F12: =-Model!I117 -> -75000000 | G12: =-Model!J117 -> -75000000 | H12: =-Model!K117 -> -75000000 | I12: =-Model!L117 -> -75000000
C13: G&A expenses | D13: =-Model!G118 -> -58500000 | E13: =-Model!H118 -> -34020000 | F13: =-Model!I118 -> -37485000 | G13: =-Model!J118 -> -45360000 | H13: =-Model!K118 -> -48195000 | I13: =-Model!L118 -> -53550000
C14: Marketing expenses | D14: =-Model!G119 -> -11700000 | E14: =-Model!H119 -> -6804000 | F14: =-Model!I119 -> -7497000 | G14: =-Model!J119 -> -9072000 | H14: =-Model!K119 -> -9639000 | I14: =-Model!L119 -> -10710000
C15: Interest expense
C16: Total | D16: =SUM(D8:D15) -> 3.3529915e+08 | E16: =SUM(E8:E15) -> -566451.28 | F16: =SUM(F8:F15) -> 46973349 | G16: =SUM(G8:G15) -> 1.5501835e+08 | H16: =SUM(H8:H15) -> 1.9391455e+08 | I16: =SUM(I8:I15) -> 2.6738515e+08
B17: 2 | C17: Cashflow from investment
C18: Capex | D18: =-(Capex!E4) -> -2959200000 | E18: 0 | F18: 0 | G18: 0 | H18: 0 | I18: 0
D19: =Capex!E6 | E19: 0 | F19: 0 | G19: 0 | H19: 0 | I19: 0
D20: =Capex!E7 | E20: 0 | F20: 0 | G20: 0 | H20: 0 | I20: 0
D21: =Capex!E8 | E21: 0 | F21: 0 | G21: 0 | H21: 0 | I21: 0
D22: =Capex!E9 | E22: 0 | F22: 0 | G22: 0 | H22: 0 | I22: 0
D23: =Capex!E10 | E23: 0 | F23: 0 | G23: 0 | H23: 0 | I23: 0
D24: =Capex!E11 | E24: 0 | F24: 0 | G24: 0 | H24: 0 | I24: 0
D25: =Capex!E12 | E25: 0 | F25: 0 | G25: 0 | H25: 0 | I25: 0
D26: =Capex!E13 | E26: 0 | F26: 0 | G26: 0 | H26: 0 | I26: 0
D27: =Capex!E14 | E27: 0 | F27: 0 | G27: 0 | H27: 0 | I27: 0
D28: =Capex!E15 | E28: 0 | F28: 0 | G28: 0 | H28: 0 | I28: 0
C29: Pre-opening costs | D29: =-(Capex!E22) -> -368000000 | E29: 0 | F29: 0 | G29: 0 | H29: 0 | I29: 0
C30: Total | D30: =SUM(D18:D29) -> -3327200000 | E30: =SUM(E18:E29) -> 0 | F30: =SUM(F18:F29) -> 0 | G30: =SUM(G18:G29) -> 0 | H30: =SUM(H18:H29) -> 0 | I30: =SUM(I18:I29) -> 0
B31: 3 | C31: Cashflow from financing
C32: Borrowings
C33: Principal repayment
C34: Total | D34: =SUM(D32:D33) -> 0 | E34: =SUM(E32:E33) -> 0 | F34: =SUM(F32:F33) -> 0 | G34: =SUM(G32:G33) -> 0 | H34: =SUM(H32:H33) -> 0 | I34: =SUM(I32:I33) -> 0
B35: 3 | C35: Net cash flow
C36: Total | D36: =D16+D30+D34 -> -2991900851 | E36: =E16+E30+E34 -> -566451.28 | F36: =F16+F30+F34 -> 46973349 | G36: =G16+G30+G34 -> 1.5501835e+08 | H36: =H16+H30+H34 -> 1.9391455e+08 | I36: =I16+I30+I34 -> 2.6738515e+08
C37: Status | D37: =IF(D36<0,"To be funded by equity","OK") -> To be funded by equity | E37: =IF(E36<0,"To be funded by equity","OK") -> To be funded by equity | F37: =IF(F36<0,"To be funded by equity","OK") -> OK | G37: =IF(G36<0,"To be funded by equity","OK") -> OK | H37: =IF(H36<0,"To be funded by equity","OK") -> OK | I37: =IF(I36<0,"To be funded by equity","OK") -> OK
B38: 4 | C38: KPI
C39: Daily order count
C40: Occupancy
C41: Average spending
B44: # | C44: Initial Capex | D44: Unit | E44: Unit Cost | F44: Cost
B45: I | C45: INITIAL OUTLAY
B46: 1 | C46: Capex
C47: Construction | D47: VND/sqm | E47: =F47/280 -> 0 | F47: =Capex!G5 -> 0
D48: VND/sqm | E48: 0
C49: Equipments (all) | D49: VND/sqm | E49: =F49/280 -> 0 | F49: =Capex!G10
C50: BOH Fixture + Supply | D50: VND/sqm | E50: =F50/280 -> 0 | F50: =Capex!E15
C51: Other costs | D51: VND/sqm | E51: =F51/280 -> 0 | F51: 0
C52: Contingency | D52: #
B53: 2 | C53: Working capital | D53: months
B54: 3 | C54: Pre-opening costs | D54: VND/sqm
C55: Total | D55: VND | F55: =Capex!E31 -> 4061841703

Sheet Reference
A1: DATE | B1: YEAR | C1: MONTH | D1: WEEKDAY | H1: # | I1: WEEKDAY
A2: 46174 | B2: =YEAR(A2) -> 2026 | C2: =MONTH(A2) -> 6 | D2: =VLOOKUP(WEEKDAY(A2,2),$H$2:$I$8,2,FALSE) -> Monday | H2: 1 | I2: Monday
A3: =A2+1 -> 46175 | B3: =YEAR(A3) -> 2026 | C3: =MONTH(A3) -> 6 | D3: =VLOOKUP(WEEKDAY(A3,2),$H$2:$I$8,2,FALSE) -> Tuesday | H3: 2 | I3: Tuesday
A4: =A3+1 -> 46176 | B4: =YEAR(A4) -> 2026 | C4: =MONTH(A4) -> 6 | D4: =VLOOKUP(WEEKDAY(A4,2),$H$2:$I$8,2,FALSE) -> Wednesday | H4: 3 | I4: Wednesday
A5: =A4+1 -> 46177 | B5: =YEAR(A5) -> 2026 | C5: =MONTH(A5) -> 6 | D5: =VLOOKUP(WEEKDAY(A5,2),$H$2:$I$8,2,FALSE) -> Thursday | H5: 4 | I5: Thursday
A6: =A5+1 -> 46178 | B6: =YEAR(A6) -> 2026 | C6: =MONTH(A6) -> 6 | D6: =VLOOKUP(WEEKDAY(A6,2),$H$2:$I$8,2,FALSE) -> Friday | H6: 5 | I6: Friday
A7: =A6+1 -> 46179 | B7: =YEAR(A7) -> 2026 | C7: =MONTH(A7) -> 6 | D7: =VLOOKUP(WEEKDAY(A7,2),$H$2:$I$8,2,FALSE) -> Saturday | H7: 6 | I7: Saturday
A8: =A7+1 -> 46180 | B8: =YEAR(A8) -> 2026 | C8: =MONTH(A8) -> 6 | D8: =VLOOKUP(WEEKDAY(A8,2),$H$2:$I$8,2,FALSE) -> Sunday | H8: 7 | I8: Sunday
A9: =A8+1 -> 46181 | B9: =YEAR(A9) -> 2026 | C9: =MONTH(A9) -> 6 | D9: =VLOOKUP(WEEKDAY(A9,2),$H$2:$I$8,2,FALSE) -> Monday
A10: =A9+1 -> 46182 | B10: =YEAR(A10) -> 2026 | C10: =MONTH(A10) -> 6 | D10: =VLOOKUP(WEEKDAY(A10,2),$H$2:$I$8,2,FALSE) -> Tuesday
A11: =A10+1 -> 46183 | B11: =YEAR(A11) -> 2026 | C11: =MONTH(A11) -> 6 | D11: =VLOOKUP(WEEKDAY(A11,2),$H$2:$I$8,2,FALSE) -> Wednesday | H11: # | I11: MONTH
A12: =A11+1 -> 46184 | B12: =YEAR(A12) -> 2026 | C12: =MONTH(A12) -> 6 | D12: =VLOOKUP(WEEKDAY(A12,2),$H$2:$I$8,2,FALSE) -> Thursday | H12: 1 | I12: Jan
A13: =A12+1 -> 46185 | B13: =YEAR(A13) -> 2026 | C13: =MONTH(A13) -> 6 | D13: =VLOOKUP(WEEKDAY(A13,2),$H$2:$I$8,2,FALSE) -> Friday | H13: 2 | I13: Feb
A14: =A13+1 -> 46186 | B14: =YEAR(A14) -> 2026 | C14: =MONTH(A14) -> 6 | D14: =VLOOKUP(WEEKDAY(A14,2),$H$2:$I$8,2,FALSE) -> Saturday | H14: 3 | I14: Mar
A15: =A14+1 -> 46187 | B15: =YEAR(A15) -> 2026 | C15: =MONTH(A15) -> 6 | D15: =VLOOKUP(WEEKDAY(A15,2),$H$2:$I$8,2,FALSE) -> Sunday | H15: 4 | I15: Apr
A16: =A15+1 -> 46188 | B16: =YEAR(A16) -> 2026 | C16: =MONTH(A16) -> 6 | D16: =VLOOKUP(WEEKDAY(A16,2),$H$2:$I$8,2,FALSE) -> Monday | H16: 5 | I16: May
A17: =A16+1 -> 46189 | B17: =YEAR(A17) -> 2026 | C17: =MONTH(A17) -> 6 | D17: =VLOOKUP(WEEKDAY(A17,2),$H$2:$I$8,2,FALSE) -> Tuesday | H17: 6 | I17: Jun
A18: =A17+1 -> 46190 | B18: =YEAR(A18) -> 2026 | C18: =MONTH(A18) -> 6 | D18: =VLOOKUP(WEEKDAY(A18,2),$H$2:$I$8,2,FALSE) -> Wednesday | H18: 7 | I18: Jul
A19: =A18+1 -> 46191 | B19: =YEAR(A19) -> 2026 | C19: =MONTH(A19) -> 6 | D19: =VLOOKUP(WEEKDAY(A19,2),$H$2:$I$8,2,FALSE) -> Thursday | H19: 8 | I19: Aug
A20: =A19+1 -> 46192 | B20: =YEAR(A20) -> 2026 | C20: =MONTH(A20) -> 6 | D20: =VLOOKUP(WEEKDAY(A20,2),$H$2:$I$8,2,FALSE) -> Friday | H20: 9 | I20: Sep
A21: =A20+1 -> 46193 | B21: =YEAR(A21) -> 2026 | C21: =MONTH(A21) -> 6 | D21: =VLOOKUP(WEEKDAY(A21,2),$H$2:$I$8,2,FALSE) -> Saturday | H21: 10 | I21: Oct
A22: =A21+1 -> 46194 | B22: =YEAR(A22) -> 2026 | C22: =MONTH(A22) -> 6 | D22: =VLOOKUP(WEEKDAY(A22,2),$H$2:$I$8,2,FALSE) -> Sunday | H22: 11 | I22: Nov
A23: =A22+1 -> 46195 | B23: =YEAR(A23) -> 2026 | C23: =MONTH(A23) -> 6 | D23: =VLOOKUP(WEEKDAY(A23,2),$H$2:$I$8,2,FALSE) -> Monday | H23: 12 | I23: Dec
A24: =A23+1 -> 46196 | B24: =YEAR(A24) -> 2026 | C24: =MONTH(A24) -> 6 | D24: =VLOOKUP(WEEKDAY(A24,2),$H$2:$I$8,2,FALSE) -> Tuesday
A25: =A24+1 -> 46197 | B25: =YEAR(A25) -> 2026 | C25: =MONTH(A25) -> 6 | D25: =VLOOKUP(WEEKDAY(A25,2),$H$2:$I$8,2,FALSE) -> Wednesday | H25: # | I25: SCENARIO
A26: =A25+1 -> 46198 | B26: =YEAR(A26) -> 2026 | C26: =MONTH(A26) -> 6 | D26: =VLOOKUP(WEEKDAY(A26,2),$H$2:$I$8,2,FALSE) -> Thursday | H26: 1 | I26: Base Case
A27: =A26+1 -> 46199 | B27: =YEAR(A27) -> 2026 | C27: =MONTH(A27) -> 6 | D27: =VLOOKUP(WEEKDAY(A27,2),$H$2:$I$8,2,FALSE) -> Friday | H27: 2 | I27: Best Case
A28: =A27+1 -> 46200 | B28: =YEAR(A28) -> 2026 | C28: =MONTH(A28) -> 6 | D28: =VLOOKUP(WEEKDAY(A28,2),$H$2:$I$8,2,FALSE) -> Saturday | H28: 3 | I28: Worst Case
A29: =A28+1 -> 46201 | B29: =YEAR(A29) -> 2026 | C29: =MONTH(A29) -> 6 | D29: =VLOOKUP(WEEKDAY(A29,2),$H$2:$I$8,2,FALSE) -> Sunday
A30: =A29+1 -> 46202 | B30: =YEAR(A30) -> 2026 | C30: =MONTH(A30) -> 6 | D30: =VLOOKUP(WEEKDAY(A30,2),$H$2:$I$8,2,FALSE) -> Monday
A31: =A30+1 -> 46203 | B31: =YEAR(A31) -> 2026 | C31: =MONTH(A31) -> 6 | D31: =VLOOKUP(WEEKDAY(A31,2),$H$2:$I$8,2,FALSE) -> Tuesday
A32: =A31+1 -> 46204 | B32: =YEAR(A32) -> 2026 | C32: =MONTH(A32) -> 7 | D32: =VLOOKUP(WEEKDAY(A32,2),$H$2:$I$8,2,FALSE) -> Wednesday
A33: =A32+1 -> 46205 | B33: =YEAR(A33) -> 2026 | C33: =MONTH(A33) -> 7 | D33: =VLOOKUP(WEEKDAY(A33,2),$H$2:$I$8,2,FALSE) -> Thursday
A34: =A33+1 -> 46206 | B34: =YEAR(A34) -> 2026 | C34: =MONTH(A34) -> 7 | D34: =VLOOKUP(WEEKDAY(A34,2),$H$2:$I$8,2,FALSE) -> Friday
A35: =A34+1 -> 46207 | B35: =YEAR(A35) -> 2026 | C35: =MONTH(A35) -> 7 | D35: =VLOOKUP(WEEKDAY(A35,2),$H$2:$I$8,2,FALSE) -> Saturday
A36: =A35+1 -> 46208 | B36: =YEAR(A36) -> 2026 | C36: =MONTH(A36) -> 7 | D36: =VLOOKUP(WEEKDAY(A36,2),$H$2:$I$8,2,FALSE) -> Sunday
A37: =A36+1 -> 46209 | B37: =YEAR(A37) -> 2026 | C37: =MONTH(A37) -> 7 | D37: =VLOOKUP(WEEKDAY(A37,2),$H$2:$I$8,2,FALSE) -> Monday
A38: =A37+1 -> 46210 | B38: =YEAR(A38) -> 2026 | C38: =MONTH(A38) -> 7 | D38: =VLOOKUP(WEEKDAY(A38,2),$H$2:$I$8,2,FALSE) -> Tuesday
A39: =A38+1 -> 46211 | B39: =YEAR(A39) -> 2026 | C39: =MONTH(A39) -> 7 | D39: =VLOOKUP(WEEKDAY(A39,2),$H$2:$I$8,2,FALSE) -> Wednesday
A40: =A39+1 -> 46212 | B40: =YEAR(A40) -> 2026 | C40: =MONTH(A40) -> 7 | D40: =VLOOKUP(WEEKDAY(A40,2),$H$2:$I$8,2,FALSE) -> Thursday
... A2060: =A2059+1 -> 48232 | B2060: =YEAR(A2060) -> 2032 | C2060: =MONTH(A2060) -> 1 | D2060: =VLOOKUP(WEEKDAY(A2060,2),$H$2:$I$8,2,FALSE) -> Monday
